{
  "updated_at": "2026-01-03T09:57:46.364902+00:00",
  "umap": {
    "n_neighbors": 10,
    "metric": "correlation",
    "min_dist": 0.15,
    "random_state": 42
  },
  "groups": {
    "calendar": {
      "fi": "Kalenteri- ja kellomuuttujat",
      "en": "Calendar and time features",
      "color": "#6c757d"
    },
    "generation": {
      "fi": "Tuotanto",
      "en": "Generation",
      "color": "#1f77b4"
    },
    "transmission": {
      "fi": "Siirtokapasiteetit",
      "en": "Transmission capacity",
      "color": "#ff7f0e"
    },
    "solar": {
      "fi": "Aurinko",
      "en": "Solar irradiance",
      "color": "#f1c40f"
    },
    "temperature": {
      "fi": "Lämpötila (FMI)",
      "en": "Temperature (FMI)",
      "color": "#d62728"
    },
    "wind_speed": {
      "fi": "Tuulen nopeus (FMI)",
      "en": "Wind speed (FMI)",
      "color": "#17becf"
    },
    "baltic_wind": {
      "fi": "Itämeren tuuli (Open-Meteo)",
      "en": "Baltic wind (Open-Meteo)",
      "color": "#2ca02c"
    }
  },
  "features": [
    {
      "id": "year",
      "label": "year",
      "group": "calendar",
      "x": 0.8492993116378784,
      "y": 0.052351124584674835,
      "z": 0.7091778516769409,
      "corr_price": -0.07971521305700734,
      "mean": 2024.0208506396411,
      "std": 0.8475194932064106,
      "latest": 2026.0
    },
    {
      "id": "day_of_week_sin",
      "label": "day_of_week_sin",
      "group": "calendar",
      "x": 0.9949672818183899,
      "y": 0.0419008694589138,
      "z": 0.9006295204162598,
      "corr_price": 0.059544609398392075,
      "mean": -0.004861871507296619,
      "std": 0.706421447940988,
      "latest": -0.7818314824680299
    },
    {
      "id": "day_of_week_cos",
      "label": "day_of_week_cos",
      "group": "calendar",
      "x": 0.7293712496757507,
      "y": 0.26692020893096924,
      "z": 0.9199078679084778,
      "corr_price": -0.11641488853333846,
      "mean": 0.005073605016395192,
      "std": 0.7077565673496377,
      "latest": 0.6234898018587334
    },
    {
      "id": "hour_sin",
      "label": "hour_sin",
      "group": "calendar",
      "x": 0.34595468640327454,
      "y": 0.13655108213424683,
      "z": 0.1324746310710907,
      "corr_price": 0.010678151593524959,
      "mean": -0.0034589571126097227,
      "std": 0.7066151303172644,
      "latest": -0.5000000000000004
    },
    {
      "id": "hour_cos",
      "label": "hour_cos",
      "group": "calendar",
      "x": 0.8516919016838074,
      "y": 0.026411494240164757,
      "z": 0.8760362267494202,
      "corr_price": -0.16421114866080996,
      "mean": 0.0046254145045576045,
      "std": 0.7075745181696904,
      "latest": 0.8660254037844384
    },
    {
      "id": "NuclearPowerMW",
      "label": "NuclearPowerMW",
      "group": "generation",
      "x": 0.7918460965156555,
      "y": 0.22632035613059998,
      "z": 0.9832310676574707,
      "corr_price": -0.003490474757970391,
      "mean": 3594.2531470079957,
      "std": 693.2777064408709,
      "latest": 4372.0
    },
    {
      "id": "ImportCapacityMW",
      "label": "ImportCapacityMW",
      "group": "transmission",
      "x": 0.754004180431366,
      "y": 0.23056714236736298,
      "z": 0.9445794224739075,
      "corr_price": 0.06603781168111417,
      "mean": 2985.7281525170292,
      "std": 614.8437450758306,
      "latest": 4114.0
    },
    {
      "id": "WindPowerMW",
      "label": "WindPowerMW",
      "group": "generation",
      "x": 0.881656289100647,
      "y": 0.13886770606040955,
      "z": 0.7208528518676758,
      "corr_price": -0.39248719138565796,
      "mean": 2159.402908705765,
      "std": 1615.9864890246374,
      "latest": 3208.0
    },
    {
      "id": "temp_mean",
      "label": "temp_mean",
      "group": "temperature",
      "x": 0.04087424650788307,
      "y": 0.6957055330276489,
      "z": 0.14679506421089172,
      "corr_price": -0.2600854496331638,
      "mean": 4.5801559409622445,
      "std": 8.579030879376194,
      "latest": -9.26896551724138
    },
    {
      "id": "temp_variance",
      "label": "temp_variance",
      "group": "temperature",
      "x": 0.7852479219436646,
      "y": 0.07927454262971878,
      "z": 0.9608554244041443,
      "corr_price": 0.192884319269377,
      "mean": 8.65632810496081,
      "std": 9.342517045750672,
      "latest": 16.383045320197045
    },
    {
      "id": "holiday",
      "label": "holiday",
      "group": "calendar",
      "x": 0.7212812304496765,
      "y": 0.2322472482919693,
      "z": 0.9373790621757507,
      "corr_price": -0.055628519662593655,
      "mean": 0.06815916265160325,
      "std": 0.35046493305452175,
      "latest": 0.0
    },
    {
      "id": "sum_irradiance",
      "label": "sum_irradiance",
      "group": "solar",
      "x": 0.34418144822120667,
      "y": 0.1402747631072998,
      "z": 0.13527868688106537,
      "corr_price": -0.05473549565306188,
      "mean": 713.2082405715236,
      "std": 1165.8712684874533,
      "latest": 0.0
    },
    {
      "id": "mean_irradiance",
      "label": "mean_irradiance",
      "group": "solar",
      "x": 0.3370271623134613,
      "y": 0.17176690697669983,
      "z": 0.16032598912715912,
      "corr_price": -0.054735495638654805,
      "mean": 101.8868915100337,
      "std": 166.55303835809352,
      "latest": 0.0
    },
    {
      "id": "std_irradiance",
      "label": "std_irradiance",
      "group": "solar",
      "x": 0.32469862699508667,
      "y": 0.2109994739294052,
      "z": 0.141930490732193,
      "corr_price": -0.04548101453799049,
      "mean": 31.38146646378626,
      "std": 49.95422396368257,
      "latest": 0.0
    },
    {
      "id": "min_irradiance",
      "label": "min_irradiance",
      "group": "solar",
      "x": 0.3490993082523346,
      "y": 0.12984953820705414,
      "z": 0.16071458160877228,
      "corr_price": -0.05139341281812807,
      "mean": 57.100099684332946,
      "std": 113.86423784592169,
      "latest": 0.0
    },
    {
      "id": "max_irradiance",
      "label": "max_irradiance",
      "group": "solar",
      "x": 0.33410805463790894,
      "y": 0.2086321860551834,
      "z": 0.1620410829782486,
      "corr_price": -0.05397726651539433,
      "mean": 141.67644126931384,
      "std": 214.7022143548452,
      "latest": 0.0
    },
    {
      "id": "SE1_FI",
      "label": "SE1_FI",
      "group": "transmission",
      "x": 0.769192099571228,
      "y": 0.10531048476696014,
      "z": 0.9103480577468872,
      "corr_price": 0.052087829880035054,
      "mean": 1151.0693636816748,
      "std": 410.74914095296344,
      "latest": 1898.0
    },
    {
      "id": "SE3_FI",
      "label": "SE3_FI",
      "group": "transmission",
      "x": 0.7604466676712036,
      "y": 0.1840374618768692,
      "z": 0.952410876750946,
      "corr_price": -0.036155462604100234,
      "mean": 1087.9278119288917,
      "std": 262.6516064337575,
      "latest": 1200.0
    },
    {
      "id": "EE_FI",
      "label": "EE_FI",
      "group": "transmission",
      "x": 0.7729434370994568,
      "y": 0.33820396661758423,
      "z": 0.9626473188400269,
      "corr_price": 0.0729905952671889,
      "mean": 757.6013457384947,
      "std": 312.001291827763,
      "latest": 1016.0
    },
    {
      "id": "eu_ws_EE01",
      "label": "eu_ws_EE01",
      "group": "baltic_wind",
      "x": 0.9045063853263855,
      "y": 0.1629643440246582,
      "z": 0.9399264454841614,
      "corr_price": -0.22484187900528824,
      "mean": 6.944828459877056,
      "std": 3.1233397223825965,
      "latest": 4.83
    },
    {
      "id": "eu_ws_EE02",
      "label": "eu_ws_EE02",
      "group": "baltic_wind",
      "x": 0.9207659959793091,
      "y": 0.18663449585437775,
      "z": 0.9401257634162903,
      "corr_price": -0.20295378539520498,
      "mean": 6.143977820235919,
      "std": 2.595451365626785,
      "latest": 2.99
    },
    {
      "id": "eu_ws_DK01",
      "label": "eu_ws_DK01",
      "group": "baltic_wind",
      "x": 0.858161985874176,
      "y": 0.057321615517139435,
      "z": 0.9689662456512451,
      "corr_price": -0.11515544048418717,
      "mean": 8.122798222296064,
      "std": 3.7223629204092807,
      "latest": 6.76
    },
    {
      "id": "eu_ws_DK02",
      "label": "eu_ws_DK02",
      "group": "baltic_wind",
      "x": 0.844606876373291,
      "y": 0.0,
      "z": 0.9768719673156738,
      "corr_price": -0.11638554486534998,
      "mean": 8.987554411031732,
      "std": 4.194426063458025,
      "latest": 9.89
    },
    {
      "id": "eu_ws_DE01",
      "label": "eu_ws_DE01",
      "group": "baltic_wind",
      "x": 0.8406197428703308,
      "y": 0.11235635727643967,
      "z": 1.0,
      "corr_price": -0.08286849147439262,
      "mean": 6.923457800299052,
      "std": 3.018684297192379,
      "latest": 8.89
    },
    {
      "id": "eu_ws_DE02",
      "label": "eu_ws_DE02",
      "group": "baltic_wind",
      "x": 0.82136470079422,
      "y": 0.06487292796373367,
      "z": 0.9824523329734802,
      "corr_price": -0.05971776016720192,
      "mean": 6.240947831865759,
      "std": 2.7249218645808866,
      "latest": 13.41
    },
    {
      "id": "eu_ws_SE01",
      "label": "eu_ws_SE01",
      "group": "baltic_wind",
      "x": 0.8747038245201111,
      "y": 0.20320633053779602,
      "z": 0.689548671245575,
      "corr_price": -0.29142325893204724,
      "mean": 6.099371157999667,
      "std": 2.8088926285299527,
      "latest": 5.46
    },
    {
      "id": "eu_ws_SE02",
      "label": "eu_ws_SE02",
      "group": "baltic_wind",
      "x": 0.8614248633384705,
      "y": 0.24587449431419373,
      "z": 0.7085394859313965,
      "corr_price": -0.2865773367431128,
      "mean": 5.590194799800631,
      "std": 2.5710928867113876,
      "latest": 4.95
    },
    {
      "id": "eu_ws_SE03",
      "label": "eu_ws_SE03",
      "group": "baltic_wind",
      "x": 0.8500375747680664,
      "y": 0.03052779659628868,
      "z": 0.9260074496269226,
      "corr_price": -0.19698174176121416,
      "mean": 5.8630848147532815,
      "std": 2.5244737952290475,
      "latest": 9.35
    },
    {
      "id": "t_100908",
      "label": "t_100908",
      "group": "temperature",
      "x": 0.05297139659523964,
      "y": 0.8846315741539001,
      "z": 0.29439711570739746,
      "corr_price": -0.22184547873873117,
      "mean": 7.3613557069280615,
      "std": 6.790855979595587,
      "latest": -0.41
    },
    {
      "id": "t_100932",
      "label": "t_100932",
      "group": "temperature",
      "x": 0.06002768874168396,
      "y": 0.9235236644744873,
      "z": 0.3015337288379669,
      "corr_price": -0.23184534170981608,
      "mean": 7.016106911447085,
      "std": 7.235360138517639,
      "latest": -1.89
    },
    {
      "id": "t_101004",
      "label": "t_101004",
      "group": "temperature",
      "x": 0.12455548346042633,
      "y": 0.8131316304206848,
      "z": 0.022675292566418648,
      "corr_price": -0.25471976477456,
      "mean": 6.655041535138727,
      "std": 8.65744618282296,
      "latest": -6.48
    },
    {
      "id": "t_101065",
      "label": "t_101065",
      "group": "temperature",
      "x": 0.14674706757068634,
      "y": 0.7707377076148987,
      "z": 0.051584888249635696,
      "corr_price": -0.26180014440713534,
      "mean": 5.937305615550756,
      "std": 8.675687302509742,
      "latest": -6.15
    },
    {
      "id": "t_101118",
      "label": "t_101118",
      "group": "temperature",
      "x": 0.1430407464504242,
      "y": 0.7198295593261719,
      "z": 0.026224568486213684,
      "corr_price": -0.26552741869080454,
      "mean": 5.122791576673866,
      "std": 9.24820399235201,
      "latest": -7.99
    },
    {
      "id": "t_101061",
      "label": "t_101061",
      "group": "temperature",
      "x": 0.06670670211315155,
      "y": 0.980765163898468,
      "z": 0.2673032581806183,
      "corr_price": -0.2519259192508955,
      "mean": 6.265925402890846,
      "std": 7.587318120237088,
      "latest": -5.71
    },
    {
      "id": "t_101256",
      "label": "t_101256",
      "group": "temperature",
      "x": 0.07036463171243668,
      "y": 1.0,
      "z": 0.2551572024822235,
      "corr_price": -0.25561857747957795,
      "mean": 5.513989865426151,
      "std": 7.837584936470019,
      "latest": -8.16
    },
    {
      "id": "t_101267",
      "label": "t_101267",
      "group": "temperature",
      "x": 0.0789409726858139,
      "y": 0.9285138845443726,
      "z": 0.26041996479034424,
      "corr_price": -0.2539667274600964,
      "mean": 6.024460885125031,
      "std": 7.6095224007451705,
      "latest": -5.89
    },
    {
      "id": "t_101268",
      "label": "t_101268",
      "group": "temperature",
      "x": 0.08132446557283401,
      "y": 0.963874340057373,
      "z": 0.2835100293159485,
      "corr_price": -0.2499940570837044,
      "mean": 5.648038710749294,
      "std": 7.396154418933799,
      "latest": -6.45
    },
    {
      "id": "t_101462",
      "label": "t_101462",
      "group": "temperature",
      "x": 0.083013154566288,
      "y": 0.6956433653831482,
      "z": 0.15834547579288483,
      "corr_price": -0.2698296113592833,
      "mean": 4.639552666555906,
      "std": 9.143015561372518,
      "latest": -10.59
    },
    {
      "id": "t_101464",
      "label": "t_101464",
      "group": "temperature",
      "x": 0.03280971199274063,
      "y": 0.8008940815925598,
      "z": 0.24151277542114258,
      "corr_price": -0.24844696898732274,
      "mean": 5.047893960790829,
      "std": 7.6960814152236265,
      "latest": -5.95
    },
    {
      "id": "t_101481",
      "label": "t_101481",
      "group": "temperature",
      "x": 0.048347897827625275,
      "y": 0.8810263276100159,
      "z": 0.23993347585201263,
      "corr_price": -0.24210929741552006,
      "mean": 5.456703771390597,
      "std": 7.324470081700816,
      "latest": -6.75
    },
    {
      "id": "t_101485",
      "label": "t_101485",
      "group": "temperature",
      "x": 0.05909382179379463,
      "y": 0.7369651794433594,
      "z": 0.177323579788208,
      "corr_price": -0.2641764052859648,
      "mean": 5.00320235919588,
      "std": 8.844296834714433,
      "latest": -9.92
    },
    {
      "id": "t_101660",
      "label": "t_101660",
      "group": "temperature",
      "x": 0.013768081553280354,
      "y": 0.6814677119255066,
      "z": 0.24436119198799133,
      "corr_price": -0.25353304947352995,
      "mean": 4.481379381957136,
      "std": 8.12722558037315,
      "latest": -9.58
    },
    {
      "id": "t_101661",
      "label": "t_101661",
      "group": "temperature",
      "x": 0.024129124358296394,
      "y": 0.6938448548316956,
      "z": 0.25605887174606323,
      "corr_price": -0.24874536314911327,
      "mean": 4.40645788336933,
      "std": 8.07112197686635,
      "latest": -7.76
    },
    {
      "id": "t_101673",
      "label": "t_101673",
      "group": "temperature",
      "x": 0.018039949238300323,
      "y": 0.6174842715263367,
      "z": 0.2761887311935425,
      "corr_price": -0.22748592120858332,
      "mean": 4.147850556570859,
      "std": 7.7839521768426385,
      "latest": -6.72
    },
    {
      "id": "t_101784",
      "label": "t_101784",
      "group": "temperature",
      "x": 0.012606430798768997,
      "y": 0.5094975233078003,
      "z": 0.2399417757987976,
      "corr_price": -0.2398687338729884,
      "mean": 3.226780196045855,
      "std": 9.174641402146623,
      "latest": -10.83
    },
    {
      "id": "t_101785",
      "label": "t_101785",
      "group": "temperature",
      "x": 0.0,
      "y": 0.5964983701705933,
      "z": 0.19927355647087097,
      "corr_price": -0.24344878395281996,
      "mean": 3.6563411696295063,
      "std": 9.053692931525598,
      "latest": -12.48
    },
    {
      "id": "t_101794",
      "label": "t_101794",
      "group": "temperature",
      "x": 0.010910909622907639,
      "y": 0.5465056896209717,
      "z": 0.17474979162216187,
      "corr_price": -0.2544843160424675,
      "mean": 3.398292905798305,
      "std": 9.67375956235065,
      "latest": -12.7
    },
    {
      "id": "t_101786",
      "label": "t_101786",
      "group": "temperature",
      "x": 0.04969780147075653,
      "y": 0.6586408615112305,
      "z": 0.08031897991895676,
      "corr_price": -0.2752861979229099,
      "mean": 3.480628426648946,
      "std": 10.149860683624622,
      "latest": -12.46
    },
    {
      "id": "t_101840",
      "label": "t_101840",
      "group": "temperature",
      "x": 0.024617549031972885,
      "y": 0.4937748908996582,
      "z": 0.15099535882472992,
      "corr_price": -0.24797984766279674,
      "mean": 1.9989160713296776,
      "std": 10.358144955591015,
      "latest": -16.93
    },
    {
      "id": "t_101783",
      "label": "t_101783",
      "group": "temperature",
      "x": 0.02080042101442814,
      "y": 0.47318658232688904,
      "z": 0.24974103271961212,
      "corr_price": -0.2275124155521366,
      "mean": 3.5554780694467523,
      "std": 8.535258516044792,
      "latest": -7.98
    },
    {
      "id": "t_101846",
      "label": "t_101846",
      "group": "temperature",
      "x": 0.010358002968132496,
      "y": 0.45026108622550964,
      "z": 0.19455845654010773,
      "corr_price": -0.24372333024919088,
      "mean": 2.5342012792822723,
      "std": 9.845670835981066,
      "latest": -13.71
    },
    {
      "id": "t_101986",
      "label": "t_101986",
      "group": "temperature",
      "x": 0.03392733260989189,
      "y": 0.5975513458251953,
      "z": 0.10082650929689407,
      "corr_price": -0.25258142316829996,
      "mean": 0.05033269646120593,
      "std": 11.686738338475278,
      "latest": -18.61
    },
    {
      "id": "t_101537",
      "label": "t_101537",
      "group": "temperature",
      "x": 0.08847524970769882,
      "y": 0.7056897878646851,
      "z": 0.050788093358278275,
      "corr_price": -0.2727967451942267,
      "mean": 4.127507060973584,
      "std": 10.05336847617762,
      "latest": -12.38
    },
    {
      "id": "t_101570",
      "label": "t_101570",
      "group": "temperature",
      "x": 0.07357658445835114,
      "y": 0.7393548488616943,
      "z": 0.0313352532684803,
      "corr_price": -0.2735182860887158,
      "mean": 4.085306113972421,
      "std": 10.353924058749516,
      "latest": -13.32
    },
    {
      "id": "t_101608",
      "label": "t_101608",
      "group": "temperature",
      "x": 0.08252175897359848,
      "y": 0.848434329032898,
      "z": 0.018250441178679466,
      "corr_price": -0.2639760899053747,
      "mean": 3.7015206014288085,
      "std": 10.376285185595822,
      "latest": -13.33
    },
    {
      "id": "t_101191",
      "label": "t_101191",
      "group": "temperature",
      "x": 0.1145390197634697,
      "y": 0.7661280035972595,
      "z": 0.0,
      "corr_price": -0.24986257458685157,
      "mean": 5.287528243894335,
      "std": 9.544943881284373,
      "latest": -8.86
    },
    {
      "id": "t_101237",
      "label": "t_101237",
      "group": "temperature",
      "x": 0.1103481873869896,
      "y": 0.8658314943313599,
      "z": 0.0200839564204216,
      "corr_price": -0.24324787624456182,
      "mean": 4.993632663233095,
      "std": 9.64234189081479,
      "latest": -8.81
    },
    {
      "id": "ws_100908",
      "label": "ws_100908",
      "group": "wind_speed",
      "x": 0.8971741199493408,
      "y": 0.25536009669303894,
      "z": 0.9006586074829102,
      "corr_price": -0.11348364682239913,
      "mean": 7.152809852134905,
      "std": 3.3279788407981234,
      "latest": 11.1
    },
    {
      "id": "ws_100932",
      "label": "ws_100932",
      "group": "wind_speed",
      "x": 0.8828943967819214,
      "y": 0.2846054434776306,
      "z": 0.9201189875602722,
      "corr_price": -0.10630230341309851,
      "mean": 7.496662651603256,
      "std": 3.7012362833743087,
      "latest": 9.4
    },
    {
      "id": "ws_101004",
      "label": "ws_101004",
      "group": "wind_speed",
      "x": 0.9546508193016052,
      "y": 0.12830552458763123,
      "z": 0.9037510752677917,
      "corr_price": -0.19638758993730782,
      "mean": 4.252217976408041,
      "std": 1.916352315046421,
      "latest": 5.8
    },
    {
      "id": "ws_101065",
      "label": "ws_101065",
      "group": "wind_speed",
      "x": 0.9535539746284485,
      "y": 0.2115870863199234,
      "z": 0.9203276038169861,
      "corr_price": -0.2259855599253311,
      "mean": 3.3396868250539953,
      "std": 1.7757591905207553,
      "latest": 4.6
    },
    {
      "id": "ws_101118",
      "label": "ws_101118",
      "group": "wind_speed",
      "x": 0.9689486622810364,
      "y": 0.18856053054332733,
      "z": 0.880200207233429,
      "corr_price": -0.27003331448061246,
      "mean": 3.3197624190064796,
      "std": 1.7725615525544236,
      "latest": 4.2
    },
    {
      "id": "ws_101061",
      "label": "ws_101061",
      "group": "wind_speed",
      "x": 0.8630974292755127,
      "y": 0.4337938129901886,
      "z": 0.8390282988548279,
      "corr_price": -0.1712269488676481,
      "mean": 6.7175839009802285,
      "std": 3.4465560778317057,
      "latest": 6.9
    },
    {
      "id": "ws_101256",
      "label": "ws_101256",
      "group": "wind_speed",
      "x": 0.8577392101287842,
      "y": 0.525143027305603,
      "z": 0.7618522047996521,
      "corr_price": -0.2515091484833428,
      "mean": 6.44886193719887,
      "std": 3.26860607056742,
      "latest": 6.0
    },
    {
      "id": "ws_101267",
      "label": "ws_101267",
      "group": "wind_speed",
      "x": 0.8671239018440247,
      "y": 0.4964738190174103,
      "z": 0.7989820837974548,
      "corr_price": -0.23845303773548623,
      "mean": 6.242562572125206,
      "std": 3.102702991812119,
      "latest": 7.1
    },
    {
      "id": "ws_101268",
      "label": "ws_101268",
      "group": "wind_speed",
      "x": 0.8531122207641602,
      "y": 0.5394076704978943,
      "z": 0.751552164554596,
      "corr_price": -0.2343784478714225,
      "mean": 6.598579498255524,
      "std": 3.129268284027105,
      "latest": 6.1
    },
    {
      "id": "ws_101462",
      "label": "ws_101462",
      "group": "wind_speed",
      "x": 0.856822669506073,
      "y": 0.5276490449905396,
      "z": 0.7137116193771362,
      "corr_price": -0.2664719816860458,
      "mean": 3.5037859278949997,
      "std": 1.9120717387526502,
      "latest": 3.2
    },
    {
      "id": "ws_101464",
      "label": "ws_101464",
      "group": "wind_speed",
      "x": 0.8453521132469177,
      "y": 0.5377434492111206,
      "z": 0.6484566330909729,
      "corr_price": -0.20199859375042087,
      "mean": 6.6743951791548985,
      "std": 3.0876707716784915,
      "latest": 8.6
    },
    {
      "id": "ws_101481",
      "label": "ws_101481",
      "group": "wind_speed",
      "x": 0.8473060131072998,
      "y": 0.528523862361908,
      "z": 0.6832208633422852,
      "corr_price": -0.2332264187650769,
      "mean": 7.188089798969929,
      "std": 3.31189226807126,
      "latest": 7.8
    },
    {
      "id": "ws_101485",
      "label": "ws_101485",
      "group": "wind_speed",
      "x": 0.860945463180542,
      "y": 0.5313824415206909,
      "z": 0.689234733581543,
      "corr_price": -0.26704184382482443,
      "mean": 3.954658165808274,
      "std": 1.8393398335765045,
      "latest": 3.7
    },
    {
      "id": "ws_101660",
      "label": "ws_101660",
      "group": "wind_speed",
      "x": 0.8756461143493652,
      "y": 0.5058050751686096,
      "z": 0.6173542141914368,
      "corr_price": -0.22335268024320612,
      "mean": 6.404986293404219,
      "std": 3.2207744049706077,
      "latest": 5.3
    },
    {
      "id": "ws_101661",
      "label": "ws_101661",
      "group": "wind_speed",
      "x": 0.8760148286819458,
      "y": 0.4933074414730072,
      "z": 0.6111472249031067,
      "corr_price": -0.21497296655738263,
      "mean": 6.248481890679515,
      "std": 3.056286517029741,
      "latest": 6.5
    },
    {
      "id": "ws_101673",
      "label": "ws_101673",
      "group": "wind_speed",
      "x": 0.8781898617744446,
      "y": 0.3985414505004883,
      "z": 0.5892015099525452,
      "corr_price": -0.22688384520731472,
      "mean": 6.796280528326965,
      "std": 3.208007629148275,
      "latest": 6.8
    },
    {
      "id": "ws_101784",
      "label": "ws_101784",
      "group": "wind_speed",
      "x": 0.9022166132926941,
      "y": 0.40908685326576233,
      "z": 0.5362005233764648,
      "corr_price": -0.2062269965062542,
      "mean": 6.127145289915269,
      "std": 3.1911814695522853,
      "latest": 5.6
    },
    {
      "id": "ws_101785",
      "label": "ws_101785",
      "group": "wind_speed",
      "x": 0.9086941480636597,
      "y": 0.39123815298080444,
      "z": 0.5574958920478821,
      "corr_price": -0.22744630059010554,
      "mean": 5.498756022595115,
      "std": 2.8027198628225243,
      "latest": 4.3
    },
    {
      "id": "ws_101794",
      "label": "ws_101794",
      "group": "wind_speed",
      "x": 0.9171275496482849,
      "y": 0.360199898481369,
      "z": 0.5501189827919006,
      "corr_price": -0.21429958301381796,
      "mean": 4.691003488951653,
      "std": 2.4220688942457076,
      "latest": 4.0
    },
    {
      "id": "ws_101786",
      "label": "ws_101786",
      "group": "wind_speed",
      "x": 0.9601624011993408,
      "y": 0.16420350968837738,
      "z": 0.7191922068595886,
      "corr_price": -0.2740412059784831,
      "mean": 3.6902641634823055,
      "std": 1.9621183797871113,
      "latest": 3.8
    },
    {
      "id": "ws_101840",
      "label": "ws_101840",
      "group": "wind_speed",
      "x": 0.9290072321891785,
      "y": 0.28637686371803284,
      "z": 0.5813190937042236,
      "corr_price": -0.22643417408205946,
      "mean": 3.4936395857562164,
      "std": 1.9312183127853386,
      "latest": 2.6
    },
    {
      "id": "ws_101783",
      "label": "ws_101783",
      "group": "wind_speed",
      "x": 0.8907182812690735,
      "y": 0.2629302740097046,
      "z": 0.572872519493103,
      "corr_price": -0.21420220134136886,
      "mean": 7.174771556736999,
      "std": 3.466059734930099,
      "latest": 7.0
    },
    {
      "id": "ws_101846",
      "label": "ws_101846",
      "group": "wind_speed",
      "x": 0.9146318435668945,
      "y": 0.2591035068035126,
      "z": 0.5697281360626221,
      "corr_price": -0.19484254877356136,
      "mean": 5.286820900481807,
      "std": 2.8134019760756686,
      "latest": 4.7
    },
    {
      "id": "ws_101986",
      "label": "ws_101986",
      "group": "wind_speed",
      "x": 0.946861207485199,
      "y": 0.19308096170425415,
      "z": 0.6613715887069702,
      "corr_price": -0.2357811521204181,
      "mean": 3.1286633992357533,
      "std": 1.872291524289609,
      "latest": 1.5
    },
    {
      "id": "ws_101537",
      "label": "ws_101537",
      "group": "wind_speed",
      "x": 0.9717602133750916,
      "y": 0.10879262536764145,
      "z": 0.7952783107757568,
      "corr_price": -0.2601167342586293,
      "mean": 1.9230063133410864,
      "std": 1.1520823984966313,
      "latest": 3.6
    },
    {
      "id": "ws_101570",
      "label": "ws_101570",
      "group": "wind_speed",
      "x": 0.9907158017158508,
      "y": 0.1728876531124115,
      "z": 0.8095811605453491,
      "corr_price": -0.2573627171771121,
      "mean": 3.5858863598604414,
      "std": 1.9102216737095663,
      "latest": 3.6
    },
    {
      "id": "ws_101608",
      "label": "ws_101608",
      "group": "wind_speed",
      "x": 1.0,
      "y": 0.12188644707202911,
      "z": 0.8364357352256775,
      "corr_price": -0.21656553219430216,
      "mean": 3.4565168632663235,
      "std": 1.7849810869168898,
      "latest": 4.5
    },
    {
      "id": "ws_101191",
      "label": "ws_101191",
      "group": "wind_speed",
      "x": 0.9891437292098999,
      "y": 0.11788354814052582,
      "z": 0.9080032110214233,
      "corr_price": -0.1698884040954804,
      "mean": 3.635695298222296,
      "std": 1.659963441928501,
      "latest": 4.1
    },
    {
      "id": "ws_101237",
      "label": "ws_101237",
      "group": "wind_speed",
      "x": 0.9866621494293213,
      "y": 0.1152629554271698,
      "z": 0.9008768796920776,
      "corr_price": -0.12884453275138066,
      "mean": 3.308257185579,
      "std": 1.6023133725514618,
      "latest": 4.4
    }
  ],
  "samples": 24076
}