{
  "updated_at": "2026-06-30T18:03:15.391909+00:00",
  "umap": {
    "n_neighbors": 10,
    "metric": "correlation",
    "min_dist": 0.15,
    "random_state": 42
  },
  "groups": {
    "calendar": {
      "fi": "Kalenteri- ja kellomuuttujat",
      "en": "Calendar and time features",
      "color": "#6c757d"
    },
    "generation": {
      "fi": "Tuotanto",
      "en": "Generation",
      "color": "#1f77b4"
    },
    "transmission": {
      "fi": "Siirtokapasiteetit",
      "en": "Transmission capacity",
      "color": "#ff7f0e"
    },
    "solar": {
      "fi": "Aurinko",
      "en": "Solar irradiance",
      "color": "#f1c40f"
    },
    "hydrology": {
      "fi": "Vesitilanne (Ympäristökeskus)",
      "en": "Hydrology (Syke)",
      "color": "#8c564b"
    },
    "temperature": {
      "fi": "Lämpötila (FMI)",
      "en": "Temperature (FMI)",
      "color": "#d62728"
    },
    "wind_speed": {
      "fi": "Tuulen nopeus (FMI)",
      "en": "Wind speed (FMI)",
      "color": "#17becf"
    },
    "baltic_wind": {
      "fi": "Itämeren tuuli (Open-Meteo)",
      "en": "Baltic wind (Open-Meteo)",
      "color": "#2ca02c"
    }
  },
  "features": [
    {
      "id": "year",
      "label": "year",
      "group": "calendar",
      "x": 0.068418949842453,
      "y": 0.745152473449707,
      "z": 0.26868924498558044,
      "corr_price": 0.03294329058843798,
      "mean": 2024.3204680836066,
      "std": 1.0548775781432642,
      "latest": 2026.0
    },
    {
      "id": "day_of_week_sin",
      "label": "day_of_week_sin",
      "group": "calendar",
      "x": 0.8950988054275513,
      "y": 0.14734649658203125,
      "z": 0.9333598017692566,
      "corr_price": 0.06810662888341856,
      "mean": -0.0023308512974501727,
      "std": 0.7064042449354717,
      "latest": 0.43388373911755823
    },
    {
      "id": "day_of_week_cos",
      "label": "day_of_week_cos",
      "group": "calendar",
      "x": 0.08695152401924133,
      "y": 0.6573911309242249,
      "z": 0.25681886076927185,
      "corr_price": -0.11089779716577745,
      "mean": 0.004813984065150827,
      "std": 0.707788411480999,
      "latest": -0.900968867902419
    },
    {
      "id": "hour_sin",
      "label": "hour_sin",
      "group": "calendar",
      "x": 0.9908769726753235,
      "y": 0.03469005227088928,
      "z": 1.0,
      "corr_price": 0.006174953036219982,
      "mean": -0.0029176924127874166,
      "std": 0.7066969768459644,
      "latest": -0.7071067811865477
    },
    {
      "id": "hour_cos",
      "label": "hour_cos",
      "group": "calendar",
      "x": 0.060913920402526855,
      "y": 0.812802791595459,
      "z": 0.09130828827619553,
      "corr_price": -0.15488707668081214,
      "mean": 0.0038946619508633535,
      "std": 0.707499612435263,
      "latest": 0.7071067811865474
    },
    {
      "id": "NuclearPowerMW",
      "label": "NuclearPowerMW",
      "group": "generation",
      "x": 0.08865675330162048,
      "y": 0.7204970121383667,
      "z": 0.16609959304332733,
      "corr_price": 0.04293375131466878,
      "mean": 3629.2330542394407,
      "std": 667.5990125108175,
      "latest": 4372.0
    },
    {
      "id": "ImportCapacityMW",
      "label": "ImportCapacityMW",
      "group": "transmission",
      "x": 0.08317545056343079,
      "y": 0.6972734928131104,
      "z": 0.22073864936828613,
      "corr_price": 0.11966702381107693,
      "mean": 3113.6541186422755,
      "std": 667.5755098833474,
      "latest": 4015.0
    },
    {
      "id": "WindPowerMW",
      "label": "WindPowerMW",
      "group": "generation",
      "x": 0.034879863262176514,
      "y": 0.8844624161720276,
      "z": 0.10159880667924881,
      "corr_price": -0.40211557046822044,
      "mean": 2185.816460318635,
      "std": 1647.1955918614076,
      "latest": 1015.9
    },
    {
      "id": "temp_mean",
      "label": "temp_mean",
      "group": "temperature",
      "x": 0.8300961256027222,
      "y": 0.16724464297294617,
      "z": 0.8106632828712463,
      "corr_price": -0.31004778291398194,
      "mean": 4.2023311183513075,
      "std": 8.73804242019437,
      "latest": 15.446896551724139
    },
    {
      "id": "temp_variance",
      "label": "temp_variance",
      "group": "temperature",
      "x": 0.08186925947666168,
      "y": 0.697594404220581,
      "z": 0.11712460219860077,
      "corr_price": 0.20150332249625505,
      "mean": 8.327878927056474,
      "std": 8.916430591949963,
      "latest": 1.3937364532019703
    },
    {
      "id": "holiday",
      "label": "holiday",
      "group": "calendar",
      "x": 0.09265737235546112,
      "y": 0.6492716670036316,
      "z": 0.26112738251686096,
      "corr_price": -0.06580303581723482,
      "mean": 0.06968383208205561,
      "std": 0.3539947640492679,
      "latest": 0.0
    },
    {
      "id": "sum_irradiance",
      "label": "sum_irradiance",
      "group": "solar",
      "x": 0.9954198598861694,
      "y": 0.021740848198533058,
      "z": 0.9788148403167725,
      "corr_price": -0.07896274500102425,
      "mean": 741.4553311480032,
      "std": 1185.240257654209,
      "latest": 16.0
    },
    {
      "id": "mean_irradiance",
      "label": "mean_irradiance",
      "group": "solar",
      "x": 0.9956696629524231,
      "y": 0.007964247837662697,
      "z": 0.9952762722969055,
      "corr_price": -0.07896274498887272,
      "mean": 105.92219016384436,
      "std": 169.3200368100376,
      "latest": 2.2857142857142856
    },
    {
      "id": "std_irradiance",
      "label": "std_irradiance",
      "group": "solar",
      "x": 0.9813657999038696,
      "y": 0.030255112797021866,
      "z": 0.9789741635322571,
      "corr_price": -0.07005550660682892,
      "mean": 32.76791483562292,
      "std": 51.3408370588153,
      "latest": 5.618845839799182
    },
    {
      "id": "min_irradiance",
      "label": "min_irradiance",
      "group": "solar",
      "x": 1.0,
      "y": 0.0,
      "z": 0.9718016386032104,
      "corr_price": -0.07067475766859768,
      "mean": 59.021183602974865,
      "std": 114.96241924928354,
      "latest": 0.0
    },
    {
      "id": "max_irradiance",
      "label": "max_irradiance",
      "group": "solar",
      "x": 0.9797275066375732,
      "y": 0.017689023166894913,
      "z": 0.9677051305770874,
      "corr_price": -0.07956631350476412,
      "mean": 147.28370519192134,
      "std": 218.70023276289126,
      "latest": 15.0
    },
    {
      "id": "SE1_FI",
      "label": "SE1_FI",
      "group": "transmission",
      "x": 0.07875321805477142,
      "y": 0.6812170147895813,
      "z": 0.23242294788360596,
      "corr_price": 0.10526360721394609,
      "mean": 1235.45987099503,
      "std": 454.36582743176314,
      "latest": 1799.0
    },
    {
      "id": "SE3_FI",
      "label": "SE3_FI",
      "group": "transmission",
      "x": 0.08834762871265411,
      "y": 0.6717056632041931,
      "z": 0.1819390505552292,
      "corr_price": -0.01331270845357433,
      "mean": 1092.769024708329,
      "std": 261.28736857882853,
      "latest": 1200.0
    },
    {
      "id": "EE_FI",
      "label": "EE_FI",
      "group": "transmission",
      "x": 0.09063318371772766,
      "y": 0.7172537446022034,
      "z": 0.21608866751194,
      "corr_price": 0.09969049631165697,
      "mean": 794.6499594656516,
      "std": 302.0625453144648,
      "latest": 1016.0
    },
    {
      "id": "eu_ws_EE01",
      "label": "eu_ws_EE01",
      "group": "baltic_wind",
      "x": 0.11105203628540039,
      "y": 0.83100825548172,
      "z": 0.13835667073726654,
      "corr_price": -0.23544552310117411,
      "mean": 6.840719396566916,
      "std": 3.0621889923047823,
      "latest": 3.85
    },
    {
      "id": "eu_ws_EE02",
      "label": "eu_ws_EE02",
      "group": "baltic_wind",
      "x": 0.11553084850311279,
      "y": 0.8254125714302063,
      "z": 0.15397122502326965,
      "corr_price": -0.20266098446029399,
      "mean": 6.078116738923549,
      "std": 2.565447859455638,
      "latest": 3.0
    },
    {
      "id": "eu_ws_DK01",
      "label": "eu_ws_DK01",
      "group": "baltic_wind",
      "x": 0.10341182351112366,
      "y": 0.7625032067298889,
      "z": 0.09851732105016708,
      "corr_price": -0.08480159856592676,
      "mean": 8.052649888971134,
      "std": 3.670935925330328,
      "latest": 4.14
    },
    {
      "id": "eu_ws_DK02",
      "label": "eu_ws_DK02",
      "group": "baltic_wind",
      "x": 0.09262063354253769,
      "y": 0.772622287273407,
      "z": 0.10260365903377533,
      "corr_price": -0.07384871285812847,
      "mean": 8.944772478939763,
      "std": 4.1730168665666065,
      "latest": 7.89
    },
    {
      "id": "eu_ws_DE01",
      "label": "eu_ws_DE01",
      "group": "baltic_wind",
      "x": 0.09769559651613235,
      "y": 0.7467569708824158,
      "z": 0.08092687278985977,
      "corr_price": -0.04108115411408217,
      "mean": 6.888653202213528,
      "std": 2.9833890640793523,
      "latest": 6.86
    },
    {
      "id": "eu_ws_DE02",
      "label": "eu_ws_DE02",
      "group": "baltic_wind",
      "x": 0.08156603574752808,
      "y": 0.7629916071891785,
      "z": 0.07026512175798416,
      "corr_price": -0.03830132037795467,
      "mean": 6.156224666032217,
      "std": 2.660777796773555,
      "latest": 4.74
    },
    {
      "id": "eu_ws_SE01",
      "label": "eu_ws_SE01",
      "group": "baltic_wind",
      "x": 0.023758595809340477,
      "y": 0.9050353169441223,
      "z": 0.10525669157505035,
      "corr_price": -0.3189389577292811,
      "mean": 6.018286983187056,
      "std": 2.7976347076161625,
      "latest": 3.53
    },
    {
      "id": "eu_ws_SE02",
      "label": "eu_ws_SE02",
      "group": "baltic_wind",
      "x": 0.04274609312415123,
      "y": 0.8956267237663269,
      "z": 0.07531106472015381,
      "corr_price": -0.30864101315930365,
      "mean": 5.564222621691163,
      "std": 2.5960319028773817,
      "latest": 1.24
    },
    {
      "id": "eu_ws_SE03",
      "label": "eu_ws_SE03",
      "group": "baltic_wind",
      "x": 0.08427981287240982,
      "y": 0.795851469039917,
      "z": 0.0981472060084343,
      "corr_price": -0.21177175099244291,
      "mean": 5.798173487011385,
      "std": 2.500110990804665,
      "latest": 1.68
    },
    {
      "id": "HydroPrecip_5d_median",
      "label": "HydroPrecip_5d_median",
      "group": "hydrology",
      "x": 0.7864393591880798,
      "y": 0.19300265610218048,
      "z": 0.6281245946884155,
      "corr_price": -0.17704137581772345,
      "mean": 7.2242606887314516,
      "std": 7.155804676270948,
      "latest": 9.0
    },
    {
      "id": "HydroPrecip_5d_p10",
      "label": "HydroPrecip_5d_p10",
      "group": "hydrology",
      "x": 0.7826041579246521,
      "y": 0.19658249616622925,
      "z": 0.6227114200592041,
      "corr_price": -0.18712913695816638,
      "mean": 3.7635508089246064,
      "std": 4.207079562845983,
      "latest": 5.8
    },
    {
      "id": "HydroSWE_median",
      "label": "HydroSWE_median",
      "group": "hydrology",
      "x": 0.0816064402461052,
      "y": 0.6692303419113159,
      "z": 0.14716386795043945,
      "corr_price": 0.12644338985543993,
      "mean": 52.448882309400446,
      "std": 57.84899315222126,
      "latest": 0.0
    },
    {
      "id": "HydroSWE_p10",
      "label": "HydroSWE_p10",
      "group": "hydrology",
      "x": 0.077076755464077,
      "y": 0.6752247214317322,
      "z": 0.13053861260414124,
      "corr_price": 0.09202088626034563,
      "mean": 36.5172910366219,
      "std": 47.107469523270204,
      "latest": 0.0
    },
    {
      "id": "t_100908",
      "label": "t_100908",
      "group": "temperature",
      "x": 0.7697422504425049,
      "y": 0.23121090233325958,
      "z": 0.5760840177536011,
      "corr_price": -0.27329958052989345,
      "mean": 6.900178703605794,
      "std": 6.827984190672026,
      "latest": 17.28
    },
    {
      "id": "t_100932",
      "label": "t_100932",
      "group": "temperature",
      "x": 0.7747093439102173,
      "y": 0.21205410361289978,
      "z": 0.5613411068916321,
      "corr_price": -0.2859631134262297,
      "mean": 6.510402876176378,
      "std": 7.367291774390092,
      "latest": 16.65
    },
    {
      "id": "t_101004",
      "label": "t_101004",
      "group": "temperature",
      "x": 0.8940422534942627,
      "y": 0.091546431183815,
      "z": 0.9510460495948792,
      "corr_price": -0.30603966796012616,
      "mean": 6.258039194952592,
      "std": 8.832096651903415,
      "latest": 17.06
    },
    {
      "id": "t_101065",
      "label": "t_101065",
      "group": "temperature",
      "x": 0.9081079959869385,
      "y": 0.11113911867141724,
      "z": 0.9223667979240417,
      "corr_price": -0.30829449073682114,
      "mean": 5.634174685418209,
      "std": 8.852344041062443,
      "latest": 16.1
    },
    {
      "id": "t_101118",
      "label": "t_101118",
      "group": "temperature",
      "x": 0.8985349535942078,
      "y": 0.11816652119159698,
      "z": 0.9072018265724182,
      "corr_price": -0.3113489977740085,
      "mean": 4.850936519685595,
      "std": 9.445827833480436,
      "latest": 16.54
    },
    {
      "id": "t_101061",
      "label": "t_101061",
      "group": "temperature",
      "x": 0.7920110821723938,
      "y": 0.2381024807691574,
      "z": 0.562275767326355,
      "corr_price": -0.3030011359381411,
      "mean": 5.789950653836664,
      "std": 7.67932839181394,
      "latest": 15.18
    },
    {
      "id": "t_101256",
      "label": "t_101256",
      "group": "temperature",
      "x": 0.8002068996429443,
      "y": 0.26644372940063477,
      "z": 0.5725626349449158,
      "corr_price": -0.3042838762660964,
      "mean": 5.075492932924465,
      "std": 7.891130139818681,
      "latest": 15.03
    },
    {
      "id": "t_101267",
      "label": "t_101267",
      "group": "temperature",
      "x": 0.7862571477890015,
      "y": 0.24821530282497406,
      "z": 0.572170615196228,
      "corr_price": -0.30277693436834496,
      "mean": 5.542161371480395,
      "std": 7.64246786045603,
      "latest": 15.2
    },
    {
      "id": "t_101268",
      "label": "t_101268",
      "group": "temperature",
      "x": 0.7852898836135864,
      "y": 0.2564847767353058,
      "z": 0.6008238792419434,
      "corr_price": -0.3005722790957343,
      "mean": 5.210432483874379,
      "std": 7.46103625403551,
      "latest": 15.52
    },
    {
      "id": "t_101462",
      "label": "t_101462",
      "group": "temperature",
      "x": 0.8506299257278442,
      "y": 0.15178681910037994,
      "z": 0.8141430616378784,
      "corr_price": -0.3130992939486108,
      "mean": 4.35388777272567,
      "std": 9.297515553060457,
      "latest": 14.17
    },
    {
      "id": "t_101464",
      "label": "t_101464",
      "group": "temperature",
      "x": 0.7978996634483337,
      "y": 0.23731540143489838,
      "z": 0.6554127931594849,
      "corr_price": -0.29858809811010983,
      "mean": 4.600852807444221,
      "std": 7.773363405677225,
      "latest": 14.63
    },
    {
      "id": "t_101481",
      "label": "t_101481",
      "group": "temperature",
      "x": 0.7934248447418213,
      "y": 0.24156954884529114,
      "z": 0.6471278667449951,
      "corr_price": -0.2930063591736319,
      "mean": 4.99558175601847,
      "std": 7.356508624380805,
      "latest": 14.65
    },
    {
      "id": "t_101485",
      "label": "t_101485",
      "group": "temperature",
      "x": 0.8397446274757385,
      "y": 0.14397434890270233,
      "z": 0.7905030250549316,
      "corr_price": -0.31009556017942913,
      "mean": 4.68048958443481,
      "std": 8.996191889136782,
      "latest": 14.93
    },
    {
      "id": "t_101660",
      "label": "t_101660",
      "group": "temperature",
      "x": 0.8017261028289795,
      "y": 0.20489540696144104,
      "z": 0.7016865611076355,
      "corr_price": -0.3048398571015635,
      "mean": 4.0811948820979165,
      "std": 8.276709312603982,
      "latest": 14.52
    },
    {
      "id": "t_101661",
      "label": "t_101661",
      "group": "temperature",
      "x": 0.8025832176208496,
      "y": 0.22579799592494965,
      "z": 0.7061915397644043,
      "corr_price": -0.29992814268182283,
      "mean": 3.959237954249057,
      "std": 8.164300875210223,
      "latest": 14.36
    },
    {
      "id": "t_101673",
      "label": "t_101673",
      "group": "temperature",
      "x": 0.7981109619140625,
      "y": 0.23655132949352264,
      "z": 0.7299503087997437,
      "corr_price": -0.28040330952110937,
      "mean": 3.7073945225758695,
      "std": 7.817937056921609,
      "latest": 14.99
    },
    {
      "id": "t_101784",
      "label": "t_101784",
      "group": "temperature",
      "x": 0.8093255162239075,
      "y": 0.20833347737789154,
      "z": 0.7781696319580078,
      "corr_price": -0.29624217614565534,
      "mean": 2.7365954672024255,
      "std": 9.37078669738627,
      "latest": 14.04
    },
    {
      "id": "t_101785",
      "label": "t_101785",
      "group": "temperature",
      "x": 0.8247008323669434,
      "y": 0.19593478739261627,
      "z": 0.774808406829834,
      "corr_price": -0.297421149274658,
      "mean": 3.1785284269148075,
      "std": 9.229917598874934,
      "latest": 13.11
    },
    {
      "id": "t_101794",
      "label": "t_101794",
      "group": "temperature",
      "x": 0.8181458711624146,
      "y": 0.17725569009780884,
      "z": 0.8058472275733948,
      "corr_price": -0.30476050691620316,
      "mean": 3.0751718303901865,
      "std": 9.835288112716185,
      "latest": 16.32
    },
    {
      "id": "t_101786",
      "label": "t_101786",
      "group": "temperature",
      "x": 0.8372994065284729,
      "y": 0.15678921341896057,
      "z": 0.8755351305007935,
      "corr_price": -0.32037768743363676,
      "mean": 3.153563850410631,
      "std": 10.247694823553378,
      "latest": 15.91
    },
    {
      "id": "t_101840",
      "label": "t_101840",
      "group": "temperature",
      "x": 0.823038637638092,
      "y": 0.19489528238773346,
      "z": 0.84818035364151,
      "corr_price": -0.29919811834042875,
      "mean": 1.6741705732379308,
      "std": 10.61675845705306,
      "latest": 14.15
    },
    {
      "id": "t_101783",
      "label": "t_101783",
      "group": "temperature",
      "x": 0.8027845025062561,
      "y": 0.22214457392692566,
      "z": 0.7594555616378784,
      "corr_price": -0.2887270219912871,
      "mean": 3.0810165309647175,
      "std": 8.744136906092825,
      "latest": 16.9
    },
    {
      "id": "t_101846",
      "label": "t_101846",
      "group": "temperature",
      "x": 0.8061694502830505,
      "y": 0.20680350065231323,
      "z": 0.8192316293716431,
      "corr_price": -0.29898308972661125,
      "mean": 2.0808487540093754,
      "std": 10.052771807665447,
      "latest": 15.06
    },
    {
      "id": "t_101986",
      "label": "t_101986",
      "group": "temperature",
      "x": 0.8363931775093079,
      "y": 0.17796702682971954,
      "z": 0.8881790637969971,
      "corr_price": -0.29376406653579373,
      "mean": -0.14895104155651934,
      "std": 11.803187013023674,
      "latest": 13.22
    },
    {
      "id": "t_101537",
      "label": "t_101537",
      "group": "temperature",
      "x": 0.8680776357650757,
      "y": 0.12433986365795135,
      "z": 0.8982328772544861,
      "corr_price": -0.31757903378556934,
      "mean": 3.8545423143350606,
      "std": 10.215260872379819,
      "latest": 15.79
    },
    {
      "id": "t_101570",
      "label": "t_101570",
      "group": "temperature",
      "x": 0.853904664516449,
      "y": 0.12927471101284027,
      "z": 0.9018872976303101,
      "corr_price": -0.3174145166657568,
      "mean": 3.8443135596207396,
      "std": 10.510970458817434,
      "latest": 16.62
    },
    {
      "id": "t_101608",
      "label": "t_101608",
      "group": "temperature",
      "x": 0.8604025840759277,
      "y": 0.10823088884353638,
      "z": 0.9290421009063721,
      "corr_price": -0.3083541249055971,
      "mean": 3.4543727750167426,
      "std": 10.548822437624954,
      "latest": 15.91
    },
    {
      "id": "t_101191",
      "label": "t_101191",
      "group": "temperature",
      "x": 0.893046498298645,
      "y": 0.0886082723736763,
      "z": 0.9304991364479065,
      "corr_price": -0.2977566210261497,
      "mean": 5.011969264389693,
      "std": 9.75092163500027,
      "latest": 17.08
    },
    {
      "id": "t_101237",
      "label": "t_101237",
      "group": "temperature",
      "x": 0.8857706785202026,
      "y": 0.09957339614629745,
      "z": 0.8993707299232483,
      "corr_price": -0.29302842123199246,
      "mean": 4.721051425751648,
      "std": 9.838348152805185,
      "latest": 17.04
    },
    {
      "id": "ws_100908",
      "label": "ws_100908",
      "group": "wind_speed",
      "x": 0.11296213418245316,
      "y": 0.8422195315361023,
      "z": 0.07011067867279053,
      "corr_price": -0.09919029839656522,
      "mean": 7.056214091854358,
      "std": 3.2881665811778755,
      "latest": 4.6
    },
    {
      "id": "ws_100932",
      "label": "ws_100932",
      "group": "wind_speed",
      "x": 0.12455205619335175,
      "y": 0.8209912180900574,
      "z": 0.09822937101125717,
      "corr_price": -0.10692458368696017,
      "mean": 7.227949314440802,
      "std": 3.597970565154637,
      "latest": 4.9
    },
    {
      "id": "ws_101004",
      "label": "ws_101004",
      "group": "wind_speed",
      "x": 0.12051162123680115,
      "y": 0.8511770963668823,
      "z": 0.24505655467510223,
      "corr_price": -0.17501008238893218,
      "mean": 4.219350745479539,
      "std": 1.8892127156811982,
      "latest": 3.1
    },
    {
      "id": "ws_101065",
      "label": "ws_101065",
      "group": "wind_speed",
      "x": 0.11633149534463882,
      "y": 0.8469311594963074,
      "z": 0.2181742638349533,
      "corr_price": -0.20784887172167388,
      "mean": 3.3441753903633993,
      "std": 1.7285073485690554,
      "latest": 2.4
    },
    {
      "id": "ws_101118",
      "label": "ws_101118",
      "group": "wind_speed",
      "x": 0.09606282413005829,
      "y": 0.8592255711555481,
      "z": 0.2459464967250824,
      "corr_price": -0.2575769949196686,
      "mean": 3.304952239963343,
      "std": 1.7272730982496303,
      "latest": 2.8
    },
    {
      "id": "ws_101061",
      "label": "ws_101061",
      "group": "wind_speed",
      "x": 0.10416314005851746,
      "y": 0.8754725456237793,
      "z": 0.05254264920949936,
      "corr_price": -0.17921708843557105,
      "mean": 6.473855345246907,
      "std": 3.336996246591294,
      "latest": 6.0
    },
    {
      "id": "ws_101256",
      "label": "ws_101256",
      "group": "wind_speed",
      "x": 0.08400096744298935,
      "y": 0.919691801071167,
      "z": 0.018415426835417747,
      "corr_price": -0.24189881321095535,
      "mean": 6.260512495153502,
      "std": 3.169432071351158,
      "latest": 3.7
    },
    {
      "id": "ws_101267",
      "label": "ws_101267",
      "group": "wind_speed",
      "x": 0.0909755602478981,
      "y": 0.9068524241447449,
      "z": 0.032155025750398636,
      "corr_price": -0.2264661012311896,
      "mean": 6.115439585720859,
      "std": 3.0153172137667865,
      "latest": 5.4
    },
    {
      "id": "ws_101268",
      "label": "ws_101268",
      "group": "wind_speed",
      "x": 0.08118093013763428,
      "y": 0.9292428493499756,
      "z": 0.03099072352051735,
      "corr_price": -0.23011714985646772,
      "mean": 6.3895773853582885,
      "std": 3.057287852883149,
      "latest": 4.1
    },
    {
      "id": "ws_101462",
      "label": "ws_101462",
      "group": "wind_speed",
      "x": 0.06855060905218124,
      "y": 0.9691303372383118,
      "z": 0.05944659560918808,
      "corr_price": -0.2569566824975589,
      "mean": 3.489346515808396,
      "std": 1.8688977042729766,
      "latest": 1.9
    },
    {
      "id": "ws_101464",
      "label": "ws_101464",
      "group": "wind_speed",
      "x": 0.046291641891002655,
      "y": 0.9690518975257874,
      "z": 0.022802310064435005,
      "corr_price": -0.18418937698526272,
      "mean": 6.5829945484238594,
      "std": 3.051705497234247,
      "latest": 2.3
    },
    {
      "id": "ws_101481",
      "label": "ws_101481",
      "group": "wind_speed",
      "x": 0.04995037242770195,
      "y": 0.9450782537460327,
      "z": 0.0,
      "corr_price": -0.20525875651086314,
      "mean": 7.092106376229248,
      "std": 3.270586846390711,
      "latest": 2.3
    },
    {
      "id": "ws_101485",
      "label": "ws_101485",
      "group": "wind_speed",
      "x": 0.0638103187084198,
      "y": 0.9545008540153503,
      "z": 0.026936635375022888,
      "corr_price": -0.256388159441715,
      "mean": 3.9231944591308023,
      "std": 1.8246959596574444,
      "latest": 2.0
    },
    {
      "id": "ws_101660",
      "label": "ws_101660",
      "group": "wind_speed",
      "x": 0.03901716694235802,
      "y": 0.9826421141624451,
      "z": 0.07114293426275253,
      "corr_price": -0.23218330970913195,
      "mean": 6.143426386098481,
      "std": 3.1461250142854986,
      "latest": 3.8
    },
    {
      "id": "ws_101661",
      "label": "ws_101661",
      "group": "wind_speed",
      "x": 0.03154017776250839,
      "y": 0.985164999961853,
      "z": 0.04769851267337799,
      "corr_price": -0.21372456955204278,
      "mean": 6.1025959606640585,
      "std": 2.9828552150208942,
      "latest": 4.9
    },
    {
      "id": "ws_101673",
      "label": "ws_101673",
      "group": "wind_speed",
      "x": 0.025282280519604683,
      "y": 0.9756790399551392,
      "z": 0.08910956233739853,
      "corr_price": -0.22462342897233276,
      "mean": 6.636253568785027,
      "std": 3.1480007761493654,
      "latest": 5.7
    },
    {
      "id": "ws_101784",
      "label": "ws_101784",
      "group": "wind_speed",
      "x": 0.018907589837908745,
      "y": 1.0,
      "z": 0.14520299434661865,
      "corr_price": -0.21833436901879966,
      "mean": 5.926331465228579,
      "std": 3.1016849669892625,
      "latest": 2.7
    },
    {
      "id": "ws_101785",
      "label": "ws_101785",
      "group": "wind_speed",
      "x": 0.016066839918494225,
      "y": 0.9849402904510498,
      "z": 0.12478892505168915,
      "corr_price": -0.23962111232197794,
      "mean": 5.276826689224912,
      "std": 2.73173090064515,
      "latest": 2.9
    },
    {
      "id": "ws_101794",
      "label": "ws_101794",
      "group": "wind_speed",
      "x": 0.01622822694480419,
      "y": 0.9779649376869202,
      "z": 0.17580895125865936,
      "corr_price": -0.22880644442289055,
      "mean": 4.52555426315604,
      "std": 2.356573102037345,
      "latest": 1.6
    },
    {
      "id": "ws_101786",
      "label": "ws_101786",
      "group": "wind_speed",
      "x": 0.035876598209142685,
      "y": 0.9210882782936096,
      "z": 0.23934446275234222,
      "corr_price": -0.2681066387866492,
      "mean": 3.676461880088823,
      "std": 1.924780578966768,
      "latest": 1.3
    },
    {
      "id": "ws_101840",
      "label": "ws_101840",
      "group": "wind_speed",
      "x": 0.0038056618068367243,
      "y": 0.9912282228469849,
      "z": 0.17535580694675446,
      "corr_price": -0.23427706237621002,
      "mean": 3.4085462855263002,
      "std": 1.8818591495995538,
      "latest": 1.9
    },
    {
      "id": "ws_101783",
      "label": "ws_101783",
      "group": "wind_speed",
      "x": 0.0,
      "y": 0.972233235836029,
      "z": 0.14182014763355255,
      "corr_price": -0.22598070762487943,
      "mean": 6.934683303373163,
      "std": 3.4064590869838796,
      "latest": 4.3
    },
    {
      "id": "ws_101846",
      "label": "ws_101846",
      "group": "wind_speed",
      "x": 0.006579273380339146,
      "y": 0.9882694482803345,
      "z": 0.16439245641231537,
      "corr_price": -0.20916281491666797,
      "mean": 5.1247189031052836,
      "std": 2.7497689777628973,
      "latest": 2.1
    },
    {
      "id": "ws_101986",
      "label": "ws_101986",
      "group": "wind_speed",
      "x": 0.019683046266436577,
      "y": 0.9492166638374329,
      "z": 0.23180988430976868,
      "corr_price": -0.24325567459648792,
      "mean": 3.0829015544041445,
      "std": 1.8063780057232957,
      "latest": 3.1
    },
    {
      "id": "ws_101537",
      "label": "ws_101537",
      "group": "wind_speed",
      "x": 0.06466672569513321,
      "y": 0.8501099944114685,
      "z": 0.2862546443939209,
      "corr_price": -0.19757832255731897,
      "mean": 2.1031652039053963,
      "std": 1.2639618318379764,
      "latest": 2.6
    },
    {
      "id": "ws_101570",
      "label": "ws_101570",
      "group": "wind_speed",
      "x": 0.07082921266555786,
      "y": 0.88327956199646,
      "z": 0.28945326805114746,
      "corr_price": -0.26099695988300586,
      "mean": 3.508163265306122,
      "std": 1.8430350041241246,
      "latest": 1.5
    },
    {
      "id": "ws_101608",
      "label": "ws_101608",
      "group": "wind_speed",
      "x": 0.07478811591863632,
      "y": 0.8715077638626099,
      "z": 0.2901531457901001,
      "corr_price": -0.2178316372315595,
      "mean": 3.4374643121497304,
      "std": 1.7397286314841374,
      "latest": 1.6
    },
    {
      "id": "ws_101191",
      "label": "ws_101191",
      "group": "wind_speed",
      "x": 0.11167319864034653,
      "y": 0.8634418845176697,
      "z": 0.28027305006980896,
      "corr_price": -0.18481837027540596,
      "mean": 3.5439744809841036,
      "std": 1.6282346000876222,
      "latest": 1.2
    },
    {
      "id": "ws_101237",
      "label": "ws_101237",
      "group": "wind_speed",
      "x": 0.09855235368013382,
      "y": 0.8561443090438843,
      "z": 0.3019430637359619,
      "corr_price": -0.14304062756469044,
      "mean": 3.283786260618237,
      "std": 1.5745569389888991,
      "latest": 0.8
    }
  ],
  "samples": 28371
}