{
  "updated_at": "2026-07-11T00:02:59.694690+00:00",
  "umap": {
    "n_neighbors": 10,
    "metric": "correlation",
    "min_dist": 0.15,
    "random_state": 42
  },
  "groups": {
    "calendar": {
      "fi": "Kalenteri- ja kellomuuttujat",
      "en": "Calendar and time features",
      "color": "#6c757d"
    },
    "generation": {
      "fi": "Tuotanto",
      "en": "Generation",
      "color": "#1f77b4"
    },
    "transmission": {
      "fi": "Siirtokapasiteetit",
      "en": "Transmission capacity",
      "color": "#ff7f0e"
    },
    "solar": {
      "fi": "Aurinko",
      "en": "Solar irradiance",
      "color": "#f1c40f"
    },
    "hydrology": {
      "fi": "Vesitilanne (Ympäristökeskus)",
      "en": "Hydrology (Syke)",
      "color": "#8c564b"
    },
    "temperature": {
      "fi": "Lämpötila (FMI)",
      "en": "Temperature (FMI)",
      "color": "#d62728"
    },
    "wind_speed": {
      "fi": "Tuulen nopeus (FMI)",
      "en": "Wind speed (FMI)",
      "color": "#17becf"
    },
    "baltic_wind": {
      "fi": "Itämeren tuuli (Open-Meteo)",
      "en": "Baltic wind (Open-Meteo)",
      "color": "#2ca02c"
    }
  },
  "features": [
    {
      "id": "year",
      "label": "year",
      "group": "calendar",
      "x": 0.07732066512107849,
      "y": 0.2869337201118469,
      "z": 0.8845284581184387,
      "corr_price": 0.026311552711488842,
      "mean": 2024.3345566390549,
      "std": 1.0615536179147473,
      "latest": 2026.0
    },
    {
      "id": "day_of_week_sin",
      "label": "day_of_week_sin",
      "group": "calendar",
      "x": 0.18636253476142883,
      "y": 0.32047468423843384,
      "z": 0.876943051815033,
      "corr_price": 0.06835013807177695,
      "mean": -0.004063912024298543,
      "std": 0.7065297582754676,
      "latest": -0.7818314824680299
    },
    {
      "id": "day_of_week_cos",
      "label": "day_of_week_cos",
      "group": "calendar",
      "x": 0.041485611349344254,
      "y": 0.17156171798706055,
      "z": 0.828971266746521,
      "corr_price": -0.11050869929997267,
      "mean": 0.004247618907863122,
      "std": 0.7076589171513927,
      "latest": 0.6234898018587334
    },
    {
      "id": "hour_sin",
      "label": "hour_sin",
      "group": "calendar",
      "x": 0.7995777130126953,
      "y": 0.0,
      "z": 0.014531346037983894,
      "corr_price": 0.0061491308902142956,
      "mean": -0.002893217694005515,
      "std": 0.7067004655292068,
      "latest": -0.7071067811865477
    },
    {
      "id": "hour_cos",
      "label": "hour_cos",
      "group": "calendar",
      "x": 0.19727760553359985,
      "y": 0.14679209887981415,
      "z": 0.9236559271812439,
      "corr_price": -0.15407814472220654,
      "mean": 0.003861992038304995,
      "std": 0.7074964072910006,
      "latest": 0.7071067811865474
    },
    {
      "id": "NuclearPowerMW",
      "label": "NuclearPowerMW",
      "group": "generation",
      "x": 0.03194212540984154,
      "y": 0.11566724628210068,
      "z": 0.8778290152549744,
      "corr_price": 0.039735830068091525,
      "mean": 3633.3870262587006,
      "std": 666.3289268975992,
      "latest": 4372.0
    },
    {
      "id": "ImportCapacityMW",
      "label": "ImportCapacityMW",
      "group": "transmission",
      "x": 0.032926805317401886,
      "y": 0.19728471338748932,
      "z": 0.8597595691680908,
      "corr_price": 0.11337986325848148,
      "mean": 3121.090839187725,
      "std": 669.7141688382534,
      "latest": 4015.0
    },
    {
      "id": "WindPowerMW",
      "label": "WindPowerMW",
      "group": "generation",
      "x": 0.2894172668457031,
      "y": 0.27198898792266846,
      "z": 0.9088765382766724,
      "corr_price": -0.3966073025867221,
      "mean": 2172.8867054874,
      "std": 1646.8092843333548,
      "latest": 1144.4
    },
    {
      "id": "temp_mean",
      "label": "temp_mean",
      "group": "temperature",
      "x": 0.9477619528770447,
      "y": 0.6165680289268494,
      "z": 0.039709798991680145,
      "corr_price": -0.31256381953050366,
      "mean": 4.299215045821059,
      "std": 8.766986266495062,
      "latest": 17.57758620689655
    },
    {
      "id": "temp_variance",
      "label": "temp_variance",
      "group": "temperature",
      "x": 0.1072392538189888,
      "y": 0.10652647167444229,
      "z": 0.8831067681312561,
      "corr_price": 0.2037196768589708,
      "mean": 8.273267332498351,
      "std": 8.899852393763274,
      "latest": 0.759633251231527
    },
    {
      "id": "holiday",
      "label": "holiday",
      "group": "calendar",
      "x": 0.03599605709314346,
      "y": 0.17358924448490143,
      "z": 0.8237992525100708,
      "corr_price": -0.06494270039160853,
      "mean": 0.0690992974729999,
      "std": 0.3525642019703476,
      "latest": 0.0
    },
    {
      "id": "sum_irradiance",
      "label": "sum_irradiance",
      "group": "solar",
      "x": 0.8384004235267639,
      "y": 0.039878182113170624,
      "z": 5.022204641136341e-05,
      "corr_price": -0.08097445167167462,
      "mean": 748.5428052147776,
      "std": 1189.7394804593512,
      "latest": 1.0
    },
    {
      "id": "mean_irradiance",
      "label": "mean_irradiance",
      "group": "solar",
      "x": 0.8224287629127502,
      "y": 0.05763186514377594,
      "z": 0.025332611054182053,
      "corr_price": -0.08097445165961618,
      "mean": 106.93468645909915,
      "std": 169.962782925031,
      "latest": 0.14285714285714285
    },
    {
      "id": "std_irradiance",
      "label": "std_irradiance",
      "group": "solar",
      "x": 0.8199032545089722,
      "y": 0.05010952427983284,
      "z": 0.0,
      "corr_price": -0.07265003991168646,
      "mean": 33.14708480265765,
      "std": 51.68739179527611,
      "latest": 0.37796447300922725
    },
    {
      "id": "min_irradiance",
      "label": "min_irradiance",
      "group": "solar",
      "x": 0.8415001034736633,
      "y": 0.09908260405063629,
      "z": 0.016535386443138123,
      "corr_price": -0.07197589977409483,
      "mean": 59.51532627311174,
      "std": 115.28034071188303,
      "latest": 0.0
    },
    {
      "id": "max_irradiance",
      "label": "max_irradiance",
      "group": "solar",
      "x": 0.8217056393623352,
      "y": 0.02309563383460045,
      "z": 0.005123288370668888,
      "corr_price": -0.08192722954613482,
      "mean": 148.80227884380133,
      "std": 219.81416193931136,
      "latest": 1.0
    },
    {
      "id": "SE1_FI",
      "label": "SE1_FI",
      "group": "transmission",
      "x": 0.06978290528059006,
      "y": 0.22553563117980957,
      "z": 0.8607032895088196,
      "corr_price": 0.09955068275759056,
      "mean": 1240.2307154590892,
      "std": 455.4234187791489,
      "latest": 1799.0
    },
    {
      "id": "SE3_FI",
      "label": "SE3_FI",
      "group": "transmission",
      "x": 0.06023973971605301,
      "y": 0.11846578121185303,
      "z": 0.8581264615058899,
      "corr_price": -0.014764451111321996,
      "mean": 1093.500751459229,
      "std": 260.43319780073904,
      "latest": 1200.0
    },
    {
      "id": "EE_FI",
      "label": "EE_FI",
      "group": "transmission",
      "x": 0.0,
      "y": 0.17043650150299072,
      "z": 0.8591406345367432,
      "corr_price": 0.09646129854859828,
      "mean": 796.5067281814687,
      "std": 301.46966447432203,
      "latest": 1016.0
    },
    {
      "id": "eu_ws_EE01",
      "label": "eu_ws_EE01",
      "group": "baltic_wind",
      "x": 0.17071810364723206,
      "y": 0.1416153758764267,
      "z": 0.9741568565368652,
      "corr_price": -0.2343828898136087,
      "mean": 6.836415364719863,
      "std": 3.0568353790615976,
      "latest": 7.11
    },
    {
      "id": "eu_ws_EE02",
      "label": "eu_ws_EE02",
      "group": "baltic_wind",
      "x": 0.14585405588150024,
      "y": 0.1831107884645462,
      "z": 0.9876096844673157,
      "corr_price": -0.2015592497046653,
      "mean": 6.074401104470308,
      "std": 2.562278833109039,
      "latest": 6.72
    },
    {
      "id": "eu_ws_DK01",
      "label": "eu_ws_DK01",
      "group": "baltic_wind",
      "x": 0.12497040629386902,
      "y": 0.0870978832244873,
      "z": 0.9300035238265991,
      "corr_price": -0.08506910491294617,
      "mean": 8.060810177903605,
      "std": 3.6761347231971624,
      "latest": 8.14
    },
    {
      "id": "eu_ws_DK02",
      "label": "eu_ws_DK02",
      "group": "baltic_wind",
      "x": 0.11217371374368668,
      "y": 0.08032017201185226,
      "z": 0.935462474822998,
      "corr_price": -0.07362130833147693,
      "mean": 8.949907727797001,
      "std": 4.188250876867877,
      "latest": 2.63
    },
    {
      "id": "eu_ws_DE01",
      "label": "eu_ws_DE01",
      "group": "baltic_wind",
      "x": 0.08170357346534729,
      "y": 0.05095287412405014,
      "z": 0.9244131445884705,
      "corr_price": -0.042201266966996234,
      "mean": 6.896342315892489,
      "std": 2.9900260430505017,
      "latest": 5.74
    },
    {
      "id": "eu_ws_DE02",
      "label": "eu_ws_DE02",
      "group": "baltic_wind",
      "x": 0.11282458901405334,
      "y": 0.06322307884693146,
      "z": 0.923557460308075,
      "corr_price": -0.03841059873199064,
      "mean": 6.155618468421237,
      "std": 2.6594762417377855,
      "latest": 5.19
    },
    {
      "id": "eu_ws_SE01",
      "label": "eu_ws_SE01",
      "group": "baltic_wind",
      "x": 0.3271098732948303,
      "y": 0.27883216738700867,
      "z": 0.9085373282432556,
      "corr_price": -0.31542383428039034,
      "mean": 6.0041057635175274,
      "std": 2.796287827171129,
      "latest": 7.06
    },
    {
      "id": "eu_ws_SE02",
      "label": "eu_ws_SE02",
      "group": "baltic_wind",
      "x": 0.31350627541542053,
      "y": 0.22395312786102295,
      "z": 0.9219392538070679,
      "corr_price": -0.3057825567251158,
      "mean": 5.553094963475586,
      "std": 2.59350706730224,
      "latest": 6.53
    },
    {
      "id": "eu_ws_SE03",
      "label": "eu_ws_SE03",
      "group": "baltic_wind",
      "x": 0.1570107340812683,
      "y": 0.11755621433258057,
      "z": 0.9392752051353455,
      "corr_price": -0.2090605497001448,
      "mean": 5.788921743385411,
      "std": 2.5015223468501517,
      "latest": 5.03
    },
    {
      "id": "HydroPrecip_5d_median",
      "label": "HydroPrecip_5d_median",
      "group": "hydrology",
      "x": 0.9466380476951599,
      "y": 1.0,
      "z": 0.04577193781733513,
      "corr_price": -0.175116826075462,
      "mean": 7.197948341546957,
      "std": 7.130277263352547,
      "latest": 4.5
    },
    {
      "id": "HydroPrecip_5d_p10",
      "label": "HydroPrecip_5d_p10",
      "group": "hydrology",
      "x": 0.9537179470062256,
      "y": 0.9874529242515564,
      "z": 0.050608888268470764,
      "corr_price": -0.18734380466342307,
      "mean": 3.772042221523191,
      "std": 4.195512758499853,
      "latest": 3.9
    },
    {
      "id": "HydroSWE_median",
      "label": "HydroSWE_median",
      "group": "hydrology",
      "x": 0.10725352168083191,
      "y": 0.15482327342033386,
      "z": 0.8674380779266357,
      "corr_price": 0.12946462067037007,
      "mean": 52.00892104435357,
      "std": 57.804118783628,
      "latest": 0.0
    },
    {
      "id": "HydroSWE_p10",
      "label": "HydroSWE_p10",
      "group": "hydrology",
      "x": 0.11784476041793823,
      "y": 0.1374882459640503,
      "z": 0.8582754731178284,
      "corr_price": 0.09476324006882453,
      "mean": 36.21097004648561,
      "std": 47.02755672573806,
      "latest": 0.0
    },
    {
      "id": "t_100908",
      "label": "t_100908",
      "group": "temperature",
      "x": 0.9901549816131592,
      "y": 0.9656143188476562,
      "z": 0.02737184427678585,
      "corr_price": -0.27627713665086445,
      "mean": 6.983961762958303,
      "std": 6.86052303072314,
      "latest": 18.24
    },
    {
      "id": "t_100932",
      "label": "t_100932",
      "group": "temperature",
      "x": 1.0,
      "y": 0.964883029460907,
      "z": 0.03516462445259094,
      "corr_price": -0.28873853053590665,
      "mean": 6.596759987417427,
      "std": 7.39767864196162,
      "latest": 18.26
    },
    {
      "id": "t_101004",
      "label": "t_101004",
      "group": "temperature",
      "x": 0.9024506211280823,
      "y": 0.33607155084609985,
      "z": 0.014096194878220558,
      "corr_price": -0.30845680177506424,
      "mean": 6.3496987172765715,
      "std": 8.854977898819557,
      "latest": 19.16
    },
    {
      "id": "t_101065",
      "label": "t_101065",
      "group": "temperature",
      "x": 0.8919366002082825,
      "y": 0.30705541372299194,
      "z": 0.009870020672678947,
      "corr_price": -0.31056786093507166,
      "mean": 5.725283632169445,
      "std": 8.876441613242518,
      "latest": 17.64
    },
    {
      "id": "t_101118",
      "label": "t_101118",
      "group": "temperature",
      "x": 0.928830087184906,
      "y": 0.36051279306411743,
      "z": 0.002812536433339119,
      "corr_price": -0.31364653605668114,
      "mean": 4.946192373562616,
      "std": 9.46780761613471,
      "latest": 18.36
    },
    {
      "id": "t_101061",
      "label": "t_101061",
      "group": "temperature",
      "x": 0.975774347782135,
      "y": 0.9513952136039734,
      "z": 0.011989747174084187,
      "corr_price": -0.3055691248589016,
      "mean": 5.87191045402118,
      "std": 7.69989617716738,
      "latest": 16.81
    },
    {
      "id": "t_101256",
      "label": "t_101256",
      "group": "temperature",
      "x": 0.9591958522796631,
      "y": 0.8847137689590454,
      "z": 0.011112518608570099,
      "corr_price": -0.306853863900578,
      "mean": 5.16016287441893,
      "std": 7.913019387844775,
      "latest": 16.79
    },
    {
      "id": "t_101267",
      "label": "t_101267",
      "group": "temperature",
      "x": 0.947242796421051,
      "y": 0.9917983412742615,
      "z": 0.012766044586896896,
      "corr_price": -0.30534503673003305,
      "mean": 5.621132441028635,
      "std": 7.659404939749055,
      "latest": 16.01
    },
    {
      "id": "t_101268",
      "label": "t_101268",
      "group": "temperature",
      "x": 0.9354791641235352,
      "y": 0.9369064569473267,
      "z": 0.02498674765229225,
      "corr_price": -0.3031998790271199,
      "mean": 5.292558107021775,
      "std": 7.484090098375203,
      "latest": 17.19
    },
    {
      "id": "t_101462",
      "label": "t_101462",
      "group": "temperature",
      "x": 0.9322616457939148,
      "y": 0.6048843264579773,
      "z": 0.009553992189466953,
      "corr_price": -0.3154121084341291,
      "mean": 4.448740694138618,
      "std": 9.320294704628147,
      "latest": 16.87
    },
    {
      "id": "t_101464",
      "label": "t_101464",
      "group": "temperature",
      "x": 0.9603791832923889,
      "y": 0.8113189935684204,
      "z": 0.04218019172549248,
      "corr_price": -0.3012575561279179,
      "mean": 4.684473978539723,
      "std": 7.794906797445598,
      "latest": 16.44
    },
    {
      "id": "t_101481",
      "label": "t_101481",
      "group": "temperature",
      "x": 0.9466042518615723,
      "y": 0.874035656452179,
      "z": 0.039098240435123444,
      "corr_price": -0.2957554952220317,
      "mean": 5.078359022753486,
      "std": 7.381477040549017,
      "latest": 17.13
    },
    {
      "id": "t_101485",
      "label": "t_101485",
      "group": "temperature",
      "x": 0.9434806108474731,
      "y": 0.6384618282318115,
      "z": 0.02475162036716938,
      "corr_price": -0.31250763308629703,
      "mean": 4.774777882632553,
      "std": 9.02022218932406,
      "latest": 17.28
    },
    {
      "id": "t_101660",
      "label": "t_101660",
      "group": "temperature",
      "x": 0.9356754422187805,
      "y": 0.7341776490211487,
      "z": 0.05067387595772743,
      "corr_price": -0.30742977572995156,
      "mean": 4.172481563035196,
      "std": 8.303263146231918,
      "latest": 17.39
    },
    {
      "id": "t_101661",
      "label": "t_101661",
      "group": "temperature",
      "x": 0.9557507634162903,
      "y": 0.7848758697509766,
      "z": 0.053606949746608734,
      "corr_price": -0.30257755667797964,
      "mean": 4.048363915976372,
      "std": 8.188949804220973,
      "latest": 16.61
    },
    {
      "id": "t_101673",
      "label": "t_101673",
      "group": "temperature",
      "x": 0.9732221961021423,
      "y": 0.8205524682998657,
      "z": 0.0760781317949295,
      "corr_price": -0.2833304128493777,
      "mean": 3.8004183705567787,
      "std": 7.85131857540838,
      "latest": 16.91
    },
    {
      "id": "t_101784",
      "label": "t_101784",
      "group": "temperature",
      "x": 0.9723923206329346,
      "y": 0.7098443508148193,
      "z": 0.08387614041566849,
      "corr_price": -0.298924422334173,
      "mean": 2.841544161336549,
      "std": 9.402564452262318,
      "latest": 17.46
    },
    {
      "id": "t_101785",
      "label": "t_101785",
      "group": "temperature",
      "x": 0.9689874053001404,
      "y": 0.6660715937614441,
      "z": 0.06509637832641602,
      "corr_price": -0.30002719847767323,
      "mean": 3.2768075215826076,
      "std": 9.255052452020927,
      "latest": 17.31
    },
    {
      "id": "t_101794",
      "label": "t_101794",
      "group": "temperature",
      "x": 0.9714471101760864,
      "y": 0.6428297162055969,
      "z": 0.0696772038936615,
      "corr_price": -0.3073567625390939,
      "mean": 3.1853136905386035,
      "std": 9.86871924140878,
      "latest": 18.98
    },
    {
      "id": "t_101786",
      "label": "t_101786",
      "group": "temperature",
      "x": 0.9507686495780945,
      "y": 0.5151045322418213,
      "z": 0.042015839368104935,
      "corr_price": -0.32279792228242793,
      "mean": 3.262037677816225,
      "std": 10.274601398748398,
      "latest": 18.54
    },
    {
      "id": "t_101840",
      "label": "t_101840",
      "group": "temperature",
      "x": 0.9374311566352844,
      "y": 0.5985065698623657,
      "z": 0.07021770626306534,
      "corr_price": -0.301781142878904,
      "mean": 1.7911671501636899,
      "std": 10.652147338806445,
      "latest": 16.54
    },
    {
      "id": "t_101783",
      "label": "t_101783",
      "group": "temperature",
      "x": 0.9783526659011841,
      "y": 0.7220513224601746,
      "z": 0.09020361304283142,
      "corr_price": -0.2915758983470547,
      "mean": 3.186070742022299,
      "std": 8.782675202926288,
      "latest": 18.17
    },
    {
      "id": "t_101846",
      "label": "t_101846",
      "group": "temperature",
      "x": 0.9577438235282898,
      "y": 0.6484568119049072,
      "z": 0.08659954369068146,
      "corr_price": -0.3016648301492231,
      "mean": 2.1949117472300865,
      "std": 10.08862313143382,
      "latest": 17.25
    },
    {
      "id": "t_101986",
      "label": "t_101986",
      "group": "temperature",
      "x": 0.9526674151420593,
      "y": 0.5651420950889587,
      "z": 0.05182017758488655,
      "corr_price": -0.29635184465314374,
      "mean": -0.023677606514977093,
      "std": 11.836393843475374,
      "latest": 16.34
    },
    {
      "id": "t_101537",
      "label": "t_101537",
      "group": "temperature",
      "x": 0.9302219152450562,
      "y": 0.45382753014564514,
      "z": 0.01771932654082775,
      "corr_price": -0.31991944610764034,
      "mean": 3.9579210793051622,
      "std": 10.237886445378756,
      "latest": 18.36
    },
    {
      "id": "t_101570",
      "label": "t_101570",
      "group": "temperature",
      "x": 0.9142913222312927,
      "y": 0.4179306626319885,
      "z": 0.02787724882364273,
      "corr_price": -0.3197966651801325,
      "mean": 3.9522680088078013,
      "std": 10.53546239668453,
      "latest": 18.91
    },
    {
      "id": "t_101608",
      "label": "t_101608",
      "group": "temperature",
      "x": 0.8956660628318787,
      "y": 0.39581993222236633,
      "z": 0.03156081959605217,
      "corr_price": -0.31080967567697454,
      "mean": 3.5649861941211425,
      "std": 10.576890903101214,
      "latest": 18.1
    },
    {
      "id": "t_101191",
      "label": "t_101191",
      "group": "temperature",
      "x": 0.9022616744041443,
      "y": 0.3293301463127136,
      "z": 0.01569080725312233,
      "corr_price": -0.30016512338502116,
      "mean": 5.110884624794659,
      "std": 9.774270607317796,
      "latest": 18.47
    },
    {
      "id": "t_101237",
      "label": "t_101237",
      "group": "temperature",
      "x": 0.8849050402641296,
      "y": 0.35989055037498474,
      "z": 0.030447402969002724,
      "corr_price": -0.29551589948291257,
      "mean": 4.821725560099263,
      "std": 9.862231117662587,
      "latest": 18.23
    },
    {
      "id": "ws_100908",
      "label": "ws_100908",
      "group": "wind_speed",
      "x": 0.2410782426595688,
      "y": 0.15252400934696198,
      "z": 0.9868391752243042,
      "corr_price": -0.09826860084801065,
      "mean": 7.049521163188984,
      "std": 3.2880508212107307,
      "latest": 4.9
    },
    {
      "id": "ws_100932",
      "label": "ws_100932",
      "group": "wind_speed",
      "x": 0.22440765798091888,
      "y": 0.13355299830436707,
      "z": 0.9798303842544556,
      "corr_price": -0.10461594669276374,
      "mean": 7.211053440984236,
      "std": 3.59383439779761,
      "latest": 4.4
    },
    {
      "id": "ws_101004",
      "label": "ws_101004",
      "group": "wind_speed",
      "x": 0.13007982075214386,
      "y": 0.2784961462020874,
      "z": 0.9949923753738403,
      "corr_price": -0.17224963064728843,
      "mean": 4.210999266016567,
      "std": 1.8884433235859375,
      "latest": 1.8
    },
    {
      "id": "ws_101065",
      "label": "ws_101065",
      "group": "wind_speed",
      "x": 0.16397318243980408,
      "y": 0.24633711576461792,
      "z": 1.0,
      "corr_price": -0.2065237870508096,
      "mean": 3.3411345286777814,
      "std": 1.728096382690379,
      "latest": 2.4
    },
    {
      "id": "ws_101118",
      "label": "ws_101118",
      "group": "wind_speed",
      "x": 0.15336322784423828,
      "y": 0.3035165071487427,
      "z": 0.9927201271057129,
      "corr_price": -0.2551234498563831,
      "mean": 3.2988326168256967,
      "std": 1.7257136159176305,
      "latest": 1.4
    },
    {
      "id": "ws_101061",
      "label": "ws_101061",
      "group": "wind_speed",
      "x": 0.2779991328716278,
      "y": 0.10316905379295349,
      "z": 0.9694555997848511,
      "corr_price": -0.17681746036530094,
      "mean": 6.459912271503967,
      "std": 3.3337756421246616,
      "latest": 3.4
    },
    {
      "id": "ws_101256",
      "label": "ws_101256",
      "group": "wind_speed",
      "x": 0.3580586612224579,
      "y": 0.13346941769123077,
      "z": 0.9600319266319275,
      "corr_price": -0.23900466046499133,
      "mean": 6.245769109782951,
      "std": 3.165213430729245,
      "latest": 3.5
    },
    {
      "id": "ws_101267",
      "label": "ws_101267",
      "group": "wind_speed",
      "x": 0.31479912996292114,
      "y": 0.12757089734077454,
      "z": 0.979162871837616,
      "corr_price": -0.2241290302380498,
      "mean": 6.104338767833577,
      "std": 3.012532853646627,
      "latest": 4.0
    },
    {
      "id": "ws_101268",
      "label": "ws_101268",
      "group": "wind_speed",
      "x": 0.34352511167526245,
      "y": 0.12987926602363586,
      "z": 0.9680212140083313,
      "corr_price": -0.22686486807416134,
      "mean": 6.373419314249764,
      "std": 3.0548862871188,
      "latest": 3.5
    },
    {
      "id": "ws_101462",
      "label": "ws_101462",
      "group": "wind_speed",
      "x": 0.3985578715801239,
      "y": 0.172346830368042,
      "z": 0.9573779106140137,
      "corr_price": -0.25525948105750684,
      "mean": 3.4851543112788788,
      "std": 1.8650121001336564,
      "latest": 1.5
    },
    {
      "id": "ws_101464",
      "label": "ws_101464",
      "group": "wind_speed",
      "x": 0.4125003516674042,
      "y": 0.19863763451576233,
      "z": 0.9420580267906189,
      "corr_price": -0.1816507971899973,
      "mean": 6.570900644274347,
      "std": 3.047700743195372,
      "latest": 3.7
    },
    {
      "id": "ws_101481",
      "label": "ws_101481",
      "group": "wind_speed",
      "x": 0.3767450749874115,
      "y": 0.19602856040000916,
      "z": 0.931596040725708,
      "corr_price": -0.20270497551987193,
      "mean": 7.078985355282932,
      "std": 3.2653681651875517,
      "latest": 4.5
    },
    {
      "id": "ws_101485",
      "label": "ws_101485",
      "group": "wind_speed",
      "x": 0.4184514880180359,
      "y": 0.21572823822498322,
      "z": 0.9584059119224548,
      "corr_price": -0.2544054759959488,
      "mean": 3.918403760791304,
      "std": 1.8216911600882337,
      "latest": 1.9
    },
    {
      "id": "ws_101660",
      "label": "ws_101660",
      "group": "wind_speed",
      "x": 0.42016464471817017,
      "y": 0.2498798966407776,
      "z": 0.9245727062225342,
      "corr_price": -0.22880257466685247,
      "mean": 6.126823599314949,
      "std": 3.1420230406274157,
      "latest": 1.6
    },
    {
      "id": "ws_101661",
      "label": "ws_101661",
      "group": "wind_speed",
      "x": 0.4349170923233032,
      "y": 0.2803646922111511,
      "z": 0.9304236173629761,
      "corr_price": -0.2110620621154786,
      "mean": 6.090536856453812,
      "std": 2.978748610731518,
      "latest": 1.2
    },
    {
      "id": "ws_101673",
      "label": "ws_101673",
      "group": "wind_speed",
      "x": 0.4139246642589569,
      "y": 0.30948951840400696,
      "z": 0.9097517132759094,
      "corr_price": -0.2217875069954605,
      "mean": 6.623947083289644,
      "std": 3.1454161131942393,
      "latest": 1.0
    },
    {
      "id": "ws_101784",
      "label": "ws_101784",
      "group": "wind_speed",
      "x": 0.444752961397171,
      "y": 0.4108196496963501,
      "z": 0.9034872651100159,
      "corr_price": -0.21600592258728965,
      "mean": 5.915614623746112,
      "std": 3.09678014119634,
      "latest": 1.8
    },
    {
      "id": "ws_101785",
      "label": "ws_101785",
      "group": "wind_speed",
      "x": 0.42990759015083313,
      "y": 0.358009934425354,
      "z": 0.8975468277931213,
      "corr_price": -0.2368378740868465,
      "mean": 5.265679284191394,
      "std": 2.728786150519927,
      "latest": 0.8
    },
    {
      "id": "ws_101794",
      "label": "ws_101794",
      "group": "wind_speed",
      "x": 0.39685821533203125,
      "y": 0.4084628224372864,
      "z": 0.8869408369064331,
      "corr_price": -0.22629017606104113,
      "mean": 4.516619482017406,
      "std": 2.3534588654448836,
      "latest": 1.4
    },
    {
      "id": "ws_101786",
      "label": "ws_101786",
      "group": "wind_speed",
      "x": 0.26346004009246826,
      "y": 0.42022085189819336,
      "z": 0.9083342552185059,
      "corr_price": -0.2665976670880145,
      "mean": 3.6742371815036172,
      "std": 1.922989218298651,
      "latest": 1.5
    },
    {
      "id": "ws_101840",
      "label": "ws_101840",
      "group": "wind_speed",
      "x": 0.3877592384815216,
      "y": 0.4439627528190613,
      "z": 0.8956522941589355,
      "corr_price": -0.23211934794654365,
      "mean": 3.4023965141612202,
      "std": 1.877913502273287,
      "latest": 1.6
    },
    {
      "id": "ws_101783",
      "label": "ws_101783",
      "group": "wind_speed",
      "x": 0.39680710434913635,
      "y": 0.3983404040336609,
      "z": 0.9123925566673279,
      "corr_price": -0.22381801656153866,
      "mean": 6.923934850232428,
      "std": 3.401721786074511,
      "latest": 4.3
    },
    {
      "id": "ws_101846",
      "label": "ws_101846",
      "group": "wind_speed",
      "x": 0.4187149107456207,
      "y": 0.4001871943473816,
      "z": 0.8852223753929138,
      "corr_price": -0.20709554986250478,
      "mean": 5.115368215022194,
      "std": 2.7433840979366444,
      "latest": 2.9
    },
    {
      "id": "ws_101986",
      "label": "ws_101986",
      "group": "wind_speed",
      "x": 0.32970452308654785,
      "y": 0.44007521867752075,
      "z": 0.8929783701896667,
      "corr_price": -0.2419904518398267,
      "mean": 3.080032155464681,
      "std": 1.8022506635150977,
      "latest": 2.0
    },
    {
      "id": "ws_101537",
      "label": "ws_101537",
      "group": "wind_speed",
      "x": 0.11780796945095062,
      "y": 0.3524225354194641,
      "z": 0.9284371137619019,
      "corr_price": -0.19844804203834127,
      "mean": 2.108297507951487,
      "std": 1.265484155393528,
      "latest": 0.7
    },
    {
      "id": "ws_101570",
      "label": "ws_101570",
      "group": "wind_speed",
      "x": 0.1383998543024063,
      "y": 0.3744838833808899,
      "z": 0.9549471735954285,
      "corr_price": -0.2579576417961961,
      "mean": 3.500747964069763,
      "std": 1.842189842536276,
      "latest": 0.9
    },
    {
      "id": "ws_101608",
      "label": "ws_101608",
      "group": "wind_speed",
      "x": 0.11699297279119492,
      "y": 0.35510945320129395,
      "z": 0.9624600410461426,
      "corr_price": -0.21515814004319625,
      "mean": 3.43062108979064,
      "std": 1.7378360674844269,
      "latest": 2.3
    },
    {
      "id": "ws_101191",
      "label": "ws_101191",
      "group": "wind_speed",
      "x": 0.09645172208547592,
      "y": 0.28170016407966614,
      "z": 0.9878586530685425,
      "corr_price": -0.18112601380714075,
      "mean": 3.5340253748558252,
      "std": 1.6284347937773775,
      "latest": 1.8
    },
    {
      "id": "ws_101237",
      "label": "ws_101237",
      "group": "wind_speed",
      "x": 0.11303236335515976,
      "y": 0.3156001567840576,
      "z": 0.9813211560249329,
      "corr_price": -0.1397133000310702,
      "mean": 3.2744713571703192,
      "std": 1.575320545649951,
      "latest": 1.4
    }
  ],
  "samples": 28611
}