{
  "updated_at": "2026-02-10T00:57:38.575635+00:00",
  "umap": {
    "n_neighbors": 10,
    "metric": "correlation",
    "min_dist": 0.15,
    "random_state": 42
  },
  "groups": {
    "calendar": {
      "fi": "Kalenteri- ja kellomuuttujat",
      "en": "Calendar and time features",
      "color": "#6c757d"
    },
    "generation": {
      "fi": "Tuotanto",
      "en": "Generation",
      "color": "#1f77b4"
    },
    "transmission": {
      "fi": "Siirtokapasiteetit",
      "en": "Transmission capacity",
      "color": "#ff7f0e"
    },
    "solar": {
      "fi": "Aurinko",
      "en": "Solar irradiance",
      "color": "#f1c40f"
    },
    "temperature": {
      "fi": "Lämpötila (FMI)",
      "en": "Temperature (FMI)",
      "color": "#d62728"
    },
    "wind_speed": {
      "fi": "Tuulen nopeus (FMI)",
      "en": "Wind speed (FMI)",
      "color": "#17becf"
    },
    "baltic_wind": {
      "fi": "Itämeren tuuli (Open-Meteo)",
      "en": "Baltic wind (Open-Meteo)",
      "color": "#2ca02c"
    }
  },
  "features": [
    {
      "id": "year",
      "label": "year",
      "group": "calendar",
      "x": 0.9286847114562988,
      "y": 0.6828987002372742,
      "z": 0.21138405799865723,
      "corr_price": 0.04197956485655542,
      "mean": 2024.0930846806466,
      "std": 0.9109433098800722,
      "latest": 2026.0
    },
    {
      "id": "day_of_week_sin",
      "label": "day_of_week_sin",
      "group": "calendar",
      "x": 0.925942063331604,
      "y": 0.7766206860542297,
      "z": 0.391292929649353,
      "corr_price": 0.06906610141274377,
      "mean": -0.0030674304599298393,
      "std": 0.7064882962088899,
      "latest": 0.9749279121818236
    },
    {
      "id": "day_of_week_cos",
      "label": "day_of_week_cos",
      "group": "calendar",
      "x": 0.8320835828781128,
      "y": 0.8490349650382996,
      "z": 0.39455780386924744,
      "corr_price": -0.10812965732605892,
      "mean": 0.006267863692180393,
      "std": 0.7076903221572057,
      "latest": -0.22252093395631434
    },
    {
      "id": "hour_sin",
      "label": "hour_sin",
      "group": "calendar",
      "x": 0.30986860394477844,
      "y": 0.09338704496622086,
      "z": 0.5960441827774048,
      "corr_price": 0.01048653346661988,
      "mean": -0.0033327137603326286,
      "std": 0.7066333780712007,
      "latest": -0.5000000000000004
    },
    {
      "id": "hour_cos",
      "label": "hour_cos",
      "group": "calendar",
      "x": 0.9480451941490173,
      "y": 0.8173474073410034,
      "z": 0.32774707674980164,
      "corr_price": -0.1666721320956303,
      "mean": 0.004456598351677959,
      "std": 0.7075579840167214,
      "latest": 0.8660254037844384
    },
    {
      "id": "NuclearPowerMW",
      "label": "NuclearPowerMW",
      "group": "generation",
      "x": 0.8820417523384094,
      "y": 0.7518422603607178,
      "z": 0.43294447660446167,
      "corr_price": 0.04318988157784267,
      "mean": 3617.3802063725866,
      "std": 690.8222733276282,
      "latest": 4372.0
    },
    {
      "id": "ImportCapacityMW",
      "label": "ImportCapacityMW",
      "group": "transmission",
      "x": 0.8644732236862183,
      "y": 0.8361403942108154,
      "z": 0.4181354343891144,
      "corr_price": 0.14681324936874343,
      "mean": 3026.353129502161,
      "std": 638.6278599781804,
      "latest": 4113.0
    },
    {
      "id": "WindPowerMW",
      "label": "WindPowerMW",
      "group": "generation",
      "x": 0.9210386872291565,
      "y": 0.6837889552116394,
      "z": 0.16679386794567108,
      "corr_price": -0.389506877230413,
      "mean": 2149.1699626780855,
      "std": 1624.4000596491337,
      "latest": 616.3
    },
    {
      "id": "temp_mean",
      "label": "temp_mean",
      "group": "temperature",
      "x": 0.06608463823795319,
      "y": 0.3149595260620117,
      "z": 0.936271071434021,
      "corr_price": -0.31250205753077503,
      "mean": 4.0832512000292605,
      "std": 8.818404669066203,
      "latest": -11.275862068965516
    },
    {
      "id": "temp_variance",
      "label": "temp_variance",
      "group": "temperature",
      "x": 0.8992148041725159,
      "y": 0.884278416633606,
      "z": 0.42426905035972595,
      "corr_price": 0.19803280450105298,
      "mean": 8.784335361332534,
      "std": 9.24946724771114,
      "latest": 11.576146551724138
    },
    {
      "id": "holiday",
      "label": "holiday",
      "group": "calendar",
      "x": 0.8299198150634766,
      "y": 0.8903716206550598,
      "z": 0.41631433367729187,
      "corr_price": -0.05827699975808346,
      "mean": 0.06663198335200897,
      "std": 0.3454556308896334,
      "latest": 0.0
    },
    {
      "id": "sum_irradiance",
      "label": "sum_irradiance",
      "group": "solar",
      "x": 0.30191168189048767,
      "y": 0.0545794852077961,
      "z": 0.6086799502372742,
      "corr_price": -0.07518848258573559,
      "mean": 690.5970145669921,
      "std": 1150.9709368217111,
      "latest": 0.0
    },
    {
      "id": "mean_irradiance",
      "label": "mean_irradiance",
      "group": "solar",
      "x": 0.295509397983551,
      "y": 0.08653639256954193,
      "z": 0.6182987093925476,
      "corr_price": -0.0751884825719483,
      "mean": 98.65671636653595,
      "std": 164.42441954863241,
      "latest": 0.0
    },
    {
      "id": "std_irradiance",
      "label": "std_irradiance",
      "group": "solar",
      "x": 0.28597721457481384,
      "y": 0.0,
      "z": 0.6315175890922546,
      "corr_price": -0.06262656543220767,
      "mean": 30.490544928744395,
      "std": 49.322124118772116,
      "latest": 0.0
    },
    {
      "id": "min_irradiance",
      "label": "min_irradiance",
      "group": "solar",
      "x": 0.2865787148475647,
      "y": 0.09528053551912308,
      "z": 0.6321660876274109,
      "corr_price": -0.07059284810663803,
      "mean": 55.14574995998079,
      "std": 112.23737736158483,
      "latest": 0.0
    },
    {
      "id": "max_irradiance",
      "label": "max_irradiance",
      "group": "solar",
      "x": 0.3024437725543976,
      "y": 0.004488454665988684,
      "z": 0.608389139175415,
      "corr_price": -0.07479667707258159,
      "mean": 137.34400512245878,
      "std": 212.1187121503899,
      "latest": 0.0
    },
    {
      "id": "SE1_FI",
      "label": "SE1_FI",
      "group": "transmission",
      "x": 0.8811156153678894,
      "y": 0.9375944137573242,
      "z": 0.39569392800331116,
      "corr_price": 0.13364874112145023,
      "mean": 1177.776332639667,
      "std": 425.94346681061546,
      "latest": 1897.0
    },
    {
      "id": "SE3_FI",
      "label": "SE3_FI",
      "group": "transmission",
      "x": 0.8578182458877563,
      "y": 0.9237254858016968,
      "z": 0.4143889844417572,
      "corr_price": -0.011672175408682694,
      "mean": 1092.018168720986,
      "std": 258.66916635756104,
      "latest": 1200.0
    },
    {
      "id": "EE_FI",
      "label": "EE_FI",
      "group": "transmission",
      "x": 0.8650218844413757,
      "y": 0.6699556112289429,
      "z": 0.4174298942089081,
      "corr_price": 0.10926548194778819,
      "mean": 767.0322554826316,
      "std": 310.06443610685443,
      "latest": 1016.0
    },
    {
      "id": "eu_ws_EE01",
      "label": "eu_ws_EE01",
      "group": "baltic_wind",
      "x": 0.9568838477134705,
      "y": 0.48228177428245544,
      "z": 0.37710416316986084,
      "corr_price": -0.2302565615278624,
      "mean": 6.908833440051224,
      "std": 3.093983617993595,
      "latest": 5.28
    },
    {
      "id": "eu_ws_EE02",
      "label": "eu_ws_EE02",
      "group": "baltic_wind",
      "x": 0.9657217860221863,
      "y": 0.4630144536495209,
      "z": 0.37178128957748413,
      "corr_price": -0.20266591622278962,
      "mean": 6.115202497198655,
      "std": 2.5847831036253517,
      "latest": 3.58
    },
    {
      "id": "eu_ws_DK01",
      "label": "eu_ws_DK01",
      "group": "baltic_wind",
      "x": 0.9389163851737976,
      "y": 0.7595694065093994,
      "z": 0.41780921816825867,
      "corr_price": -0.0806742842363134,
      "mean": 8.162312309908758,
      "std": 3.6944808786203422,
      "latest": 8.39
    },
    {
      "id": "eu_ws_DK02",
      "label": "eu_ws_DK02",
      "group": "baltic_wind",
      "x": 0.9538354277610779,
      "y": 0.8297679424285889,
      "z": 0.3935869336128235,
      "corr_price": -0.06778543900585915,
      "mean": 9.069629822314711,
      "std": 4.197841782551755,
      "latest": 8.02
    },
    {
      "id": "eu_ws_DE01",
      "label": "eu_ws_DE01",
      "group": "baltic_wind",
      "x": 0.9277911186218262,
      "y": 0.8572473526000977,
      "z": 0.4403868019580841,
      "corr_price": -0.04589790691880105,
      "mean": 6.970437810148872,
      "std": 3.002582366035842,
      "latest": 6.89
    },
    {
      "id": "eu_ws_DE02",
      "label": "eu_ws_DE02",
      "group": "baltic_wind",
      "x": 0.9375461935997009,
      "y": 0.9038996696472168,
      "z": 0.42445290088653564,
      "corr_price": -0.04010116323340982,
      "mean": 6.26018128701777,
      "std": 2.6898818922316994,
      "latest": 5.72
    },
    {
      "id": "eu_ws_SE01",
      "label": "eu_ws_SE01",
      "group": "baltic_wind",
      "x": 0.9180408716201782,
      "y": 0.7584904432296753,
      "z": 0.12119394540786743,
      "corr_price": -0.3033918578112718,
      "mean": 6.054865535457019,
      "std": 2.8042600502903077,
      "latest": 2.41
    },
    {
      "id": "eu_ws_SE02",
      "label": "eu_ws_SE02",
      "group": "baltic_wind",
      "x": 0.8937426805496216,
      "y": 0.7181960940361023,
      "z": 0.14342454075813293,
      "corr_price": -0.2941410133295655,
      "mean": 5.556731230990876,
      "std": 2.6048832542604843,
      "latest": 3.79
    },
    {
      "id": "eu_ws_SE03",
      "label": "eu_ws_SE03",
      "group": "baltic_wind",
      "x": 0.9553385376930237,
      "y": 0.722678542137146,
      "z": 0.37044012546539307,
      "corr_price": -0.1992881532636905,
      "mean": 5.838391627981432,
      "std": 2.5086935801829573,
      "latest": 0.41
    },
    {
      "id": "t_100908",
      "label": "t_100908",
      "group": "temperature",
      "x": 0.047597937285900116,
      "y": 0.9964208006858826,
      "z": 0.9942502379417419,
      "corr_price": -0.2749944809487375,
      "mean": 7.006844085160877,
      "std": 6.925540043587358,
      "latest": -3.64
    },
    {
      "id": "t_100932",
      "label": "t_100932",
      "group": "temperature",
      "x": 0.05340620502829552,
      "y": 1.0,
      "z": 0.9836857914924622,
      "corr_price": -0.2891039547310837,
      "mean": 6.595408596126142,
      "std": 7.4425908080486165,
      "latest": -5.9
    },
    {
      "id": "t_101004",
      "label": "t_101004",
      "group": "temperature",
      "x": 0.1479739099740982,
      "y": 0.15329855680465698,
      "z": 0.8693754076957703,
      "corr_price": -0.30913478521390536,
      "mean": 6.14319353289579,
      "std": 8.913892049186257,
      "latest": -9.12
    },
    {
      "id": "t_101065",
      "label": "t_101065",
      "group": "temperature",
      "x": 0.14275074005126953,
      "y": 0.09545978158712387,
      "z": 0.8414105772972107,
      "corr_price": -0.3133136862257464,
      "mean": 5.441728029454138,
      "std": 8.908297629476806,
      "latest": -8.19
    },
    {
      "id": "t_101118",
      "label": "t_101118",
      "group": "temperature",
      "x": 0.14270469546318054,
      "y": 0.20328781008720398,
      "z": 0.8669657111167908,
      "corr_price": -0.3167620228197272,
      "mean": 4.592119017128222,
      "std": 9.499010325426525,
      "latest": -10.62
    },
    {
      "id": "t_101061",
      "label": "t_101061",
      "group": "temperature",
      "x": 0.06586561352014542,
      "y": 0.9511235356330872,
      "z": 0.9702915549278259,
      "corr_price": -0.30531237613430795,
      "mean": 5.820170081639186,
      "std": 7.80902183338968,
      "latest": -8.41
    },
    {
      "id": "t_101256",
      "label": "t_101256",
      "group": "temperature",
      "x": 0.060977909713983536,
      "y": 0.8036556243896484,
      "z": 0.9577841758728027,
      "corr_price": -0.3059810257852972,
      "mean": 5.07620177685289,
      "std": 8.036339091806974,
      "latest": -9.23
    },
    {
      "id": "t_101267",
      "label": "t_101267",
      "group": "temperature",
      "x": 0.0675729438662529,
      "y": 0.9185672402381897,
      "z": 0.9633063077926636,
      "corr_price": -0.30492280496663393,
      "mean": 5.598145120468636,
      "std": 7.800705713092743,
      "latest": -9.35
    },
    {
      "id": "t_101268",
      "label": "t_101268",
      "group": "temperature",
      "x": 0.06982983648777008,
      "y": 0.8828265070915222,
      "z": 0.973871648311615,
      "corr_price": -0.3023463913178389,
      "mean": 5.223137506002882,
      "std": 7.598132466807572,
      "latest": -7.76
    },
    {
      "id": "t_101462",
      "label": "t_101462",
      "group": "temperature",
      "x": 0.08382407575845718,
      "y": 0.426415354013443,
      "z": 0.938456118106842,
      "corr_price": -0.3174108759034742,
      "mean": 4.131537938210341,
      "std": 9.372085668567872,
      "latest": -10.97
    },
    {
      "id": "t_101464",
      "label": "t_101464",
      "group": "temperature",
      "x": 0.05340886861085892,
      "y": 0.6435126066207886,
      "z": 0.9984952807426453,
      "corr_price": -0.2973450386885202,
      "mean": 4.638573115095246,
      "std": 7.859650163636718,
      "latest": -8.4
    },
    {
      "id": "t_101481",
      "label": "t_101481",
      "group": "temperature",
      "x": 0.05608987435698509,
      "y": 0.7628591656684875,
      "z": 0.9921126365661621,
      "corr_price": -0.2922510715291108,
      "mean": 5.0656955338562515,
      "std": 7.482475580356779,
      "latest": -7.58
    },
    {
      "id": "t_101485",
      "label": "t_101485",
      "group": "temperature",
      "x": 0.0739361047744751,
      "y": 0.4592605531215668,
      "z": 0.9493646621704102,
      "corr_price": -0.3134371579299129,
      "mean": 4.503695773971507,
      "std": 9.075734957047366,
      "latest": -10.57
    },
    {
      "id": "t_101660",
      "label": "t_101660",
      "group": "temperature",
      "x": 0.05909380316734314,
      "y": 0.49155446887016296,
      "z": 0.9942812919616699,
      "corr_price": -0.3055576969880069,
      "mean": 4.01468785016808,
      "std": 8.353082482793532,
      "latest": -11.0
    },
    {
      "id": "t_101661",
      "label": "t_101661",
      "group": "temperature",
      "x": 0.040200330317020416,
      "y": 0.486955463886261,
      "z": 1.0,
      "corr_price": -0.2997772889369487,
      "mean": 3.9638278373619333,
      "std": 8.262889160613794,
      "latest": -11.06
    },
    {
      "id": "t_101673",
      "label": "t_101673",
      "group": "temperature",
      "x": 0.019690249115228653,
      "y": 0.5268275737762451,
      "z": 0.991557240486145,
      "corr_price": -0.278240621300393,
      "mean": 3.747770129662238,
      "std": 7.928152790232055,
      "latest": -10.56
    },
    {
      "id": "t_101784",
      "label": "t_101784",
      "group": "temperature",
      "x": 0.010066893883049488,
      "y": 0.3404971659183502,
      "z": 0.9495469331741333,
      "corr_price": -0.29563474683118024,
      "mean": 2.6953161517528414,
      "std": 9.440113222741132,
      "latest": -15.75
    },
    {
      "id": "t_101785",
      "label": "t_101785",
      "group": "temperature",
      "x": 0.032706521451473236,
      "y": 0.3231620490550995,
      "z": 0.9738931655883789,
      "corr_price": -0.29773058291052845,
      "mean": 3.1327385144869537,
      "std": 9.314740182140095,
      "latest": -13.66
    },
    {
      "id": "t_101794",
      "label": "t_101794",
      "group": "temperature",
      "x": 0.035279374569654465,
      "y": 0.22729995846748352,
      "z": 0.9603679776191711,
      "corr_price": -0.30602873805191594,
      "mean": 2.854109972786937,
      "std": 9.92408757710582,
      "latest": -14.05
    },
    {
      "id": "t_101786",
      "label": "t_101786",
      "group": "temperature",
      "x": 0.06316082924604416,
      "y": 0.1543375551700592,
      "z": 0.9168435335159302,
      "corr_price": -0.32259016799881046,
      "mean": 2.931340643508885,
      "std": 10.38034172582113,
      "latest": -14.14
    },
    {
      "id": "t_101840",
      "label": "t_101840",
      "group": "temperature",
      "x": 0.026373738422989845,
      "y": 0.3385006785392761,
      "z": 0.9139729142189026,
      "corr_price": -0.3009484275582548,
      "mean": 1.4019814844458673,
      "std": 10.65561849116799,
      "latest": -18.23
    },
    {
      "id": "t_101783",
      "label": "t_101783",
      "group": "temperature",
      "x": 0.0,
      "y": 0.43211397528648376,
      "z": 0.9605381488800049,
      "corr_price": -0.2869725109102599,
      "mean": 3.0506287017768527,
      "std": 8.792286614101718,
      "latest": -13.92
    },
    {
      "id": "t_101846",
      "label": "t_101846",
      "group": "temperature",
      "x": 0.009804729372262955,
      "y": 0.29767829179763794,
      "z": 0.9298796653747559,
      "corr_price": -0.29917093312520116,
      "mean": 1.9611113334400512,
      "std": 10.132606241358223,
      "latest": -16.46
    },
    {
      "id": "t_101986",
      "label": "t_101986",
      "group": "temperature",
      "x": 0.037739045917987823,
      "y": 0.23439393937587738,
      "z": 0.9025613069534302,
      "corr_price": -0.29699679037150795,
      "mean": -0.5413130302545226,
      "std": 11.906278313862689,
      "latest": -16.94
    },
    {
      "id": "t_101537",
      "label": "t_101537",
      "group": "temperature",
      "x": 0.10520916432142258,
      "y": 0.144565150141716,
      "z": 0.8889523148536682,
      "corr_price": -0.3219768665090638,
      "mean": 3.5638918680966865,
      "std": 10.305917403546708,
      "latest": -12.87
    },
    {
      "id": "t_101570",
      "label": "t_101570",
      "group": "temperature",
      "x": 0.11422517895698547,
      "y": 0.060678478330373764,
      "z": 0.8855143189430237,
      "corr_price": -0.32179086026422526,
      "mean": 3.5103457659676645,
      "std": 10.60321698002354,
      "latest": -12.57
    },
    {
      "id": "t_101608",
      "label": "t_101608",
      "group": "temperature",
      "x": 0.11427779495716095,
      "y": 0.11838871985673904,
      "z": 0.9036026000976562,
      "corr_price": -0.3131571388756059,
      "mean": 3.1195673923483276,
      "std": 10.633118680383408,
      "latest": -14.45
    },
    {
      "id": "t_101191",
      "label": "t_101191",
      "group": "temperature",
      "x": 0.13196370005607605,
      "y": 0.10916531085968018,
      "z": 0.8774809837341309,
      "corr_price": -0.30222968139545286,
      "mean": 4.736534336481511,
      "std": 9.806796336268256,
      "latest": -10.65
    },
    {
      "id": "t_101237",
      "label": "t_101237",
      "group": "temperature",
      "x": 0.14387252926826477,
      "y": 0.06452955305576324,
      "z": 0.8551878929138184,
      "corr_price": -0.2964146005572285,
      "mean": 4.435295741956139,
      "std": 9.907389610469936,
      "latest": -10.95
    },
    {
      "id": "ws_100908",
      "label": "ws_100908",
      "group": "wind_speed",
      "x": 0.9223219156265259,
      "y": 0.4753420352935791,
      "z": 0.37081578373908997,
      "corr_price": -0.0966986836783922,
      "mean": 7.170271730430606,
      "std": 3.3395696955517487,
      "latest": 3.1
    },
    {
      "id": "ws_100932",
      "label": "ws_100932",
      "group": "wind_speed",
      "x": 0.9429181814193726,
      "y": 0.4149426221847534,
      "z": 0.3796340525150299,
      "corr_price": -0.10838071898223123,
      "mean": 7.470731951336641,
      "std": 3.6797500224988853,
      "latest": 4.9
    },
    {
      "id": "ws_101004",
      "label": "ws_101004",
      "group": "wind_speed",
      "x": 0.9911006689071655,
      "y": 0.32765263319015503,
      "z": 0.35196518898010254,
      "corr_price": -0.18058742116951992,
      "mean": 4.256827277093005,
      "std": 1.922004312934549,
      "latest": 3.2
    },
    {
      "id": "ws_101065",
      "label": "ws_101065",
      "group": "wind_speed",
      "x": 0.9728603959083557,
      "y": 0.3578732907772064,
      "z": 0.33600011467933655,
      "corr_price": -0.2099157618657435,
      "mean": 3.3386425484232434,
      "std": 1.7678396968228365,
      "latest": 2.6
    },
    {
      "id": "ws_101118",
      "label": "ws_101118",
      "group": "wind_speed",
      "x": 0.9839382171630859,
      "y": 0.37877508997917175,
      "z": 0.31442949175834656,
      "corr_price": -0.26155438577010953,
      "mean": 3.3042740515447413,
      "std": 1.7651684720514549,
      "latest": 1.4
    },
    {
      "id": "ws_101061",
      "label": "ws_101061",
      "group": "wind_speed",
      "x": 0.8609848022460938,
      "y": 0.39823222160339355,
      "z": 0.23282365500926971,
      "corr_price": -0.18077504052268029,
      "mean": 6.664625020009605,
      "std": 3.4176503302018504,
      "latest": 2.6
    },
    {
      "id": "ws_101256",
      "label": "ws_101256",
      "group": "wind_speed",
      "x": 0.8462429046630859,
      "y": 0.44377845525741577,
      "z": 0.16978667676448822,
      "corr_price": -0.24834890694142917,
      "mean": 6.413378421642388,
      "std": 3.2433279949616622,
      "latest": 3.5
    },
    {
      "id": "ws_101267",
      "label": "ws_101267",
      "group": "wind_speed",
      "x": 0.8538416028022766,
      "y": 0.3699401021003723,
      "z": 0.19208820164203644,
      "corr_price": -0.22988763443437746,
      "mean": 6.222552284556046,
      "std": 3.0805229203989315,
      "latest": 2.7
    },
    {
      "id": "ws_101268",
      "label": "ws_101268",
      "group": "wind_speed",
      "x": 0.8520655632019043,
      "y": 0.36522310972213745,
      "z": 0.18007507920265198,
      "corr_price": -0.2359228200128535,
      "mean": 6.557239474947974,
      "std": 3.109821583339047,
      "latest": 3.4
    },
    {
      "id": "ws_101462",
      "label": "ws_101462",
      "group": "wind_speed",
      "x": 0.8623524904251099,
      "y": 0.43533647060394287,
      "z": 0.11329428106546402,
      "corr_price": -0.2587756333313913,
      "mean": 3.4880522650872425,
      "std": 1.9000086936661513,
      "latest": 2.0
    },
    {
      "id": "ws_101464",
      "label": "ws_101464",
      "group": "wind_speed",
      "x": 0.8554675579071045,
      "y": 0.5010747313499451,
      "z": 0.09586382657289505,
      "corr_price": -0.18940723924485678,
      "mean": 6.665817125553598,
      "std": 3.0831350695993955,
      "latest": 3.9
    },
    {
      "id": "ws_101481",
      "label": "ws_101481",
      "group": "wind_speed",
      "x": 0.852141797542572,
      "y": 0.5006215572357178,
      "z": 0.1419377624988556,
      "corr_price": -0.21440648467491955,
      "mean": 7.187612053785816,
      "std": 3.307063265002033,
      "latest": 3.2
    },
    {
      "id": "ws_101485",
      "label": "ws_101485",
      "group": "wind_speed",
      "x": 0.8597379326820374,
      "y": 0.40005213022232056,
      "z": 0.11887329071760178,
      "corr_price": -0.260211142526525,
      "mean": 3.9370517848567315,
      "std": 1.8341547160420373,
      "latest": 2.4
    },
    {
      "id": "ws_101660",
      "label": "ws_101660",
      "group": "wind_speed",
      "x": 0.8818480968475342,
      "y": 0.5000352263450623,
      "z": 0.05606082081794739,
      "corr_price": -0.23754461916324457,
      "mean": 6.3388606531134934,
      "std": 3.201784589615571,
      "latest": 3.7
    },
    {
      "id": "ws_101661",
      "label": "ws_101661",
      "group": "wind_speed",
      "x": 0.8754589557647705,
      "y": 0.614626407623291,
      "z": 0.06190988048911095,
      "corr_price": -0.2159870782803211,
      "mean": 6.217802545221707,
      "std": 3.0320601161608542,
      "latest": 3.9
    },
    {
      "id": "ws_101673",
      "label": "ws_101673",
      "group": "wind_speed",
      "x": 0.8947232365608215,
      "y": 0.6490789651870728,
      "z": 0.03796027600765228,
      "corr_price": -0.22858724433274613,
      "mean": 6.766954137986233,
      "std": 3.185228683731242,
      "latest": 3.8
    },
    {
      "id": "ws_101784",
      "label": "ws_101784",
      "group": "wind_speed",
      "x": 0.9151109457015991,
      "y": 0.5964831113815308,
      "z": 0.00789614673703909,
      "corr_price": -0.22060726107399117,
      "mean": 6.0709080358572125,
      "std": 3.168313100635796,
      "latest": 2.5
    },
    {
      "id": "ws_101785",
      "label": "ws_101785",
      "group": "wind_speed",
      "x": 0.9185004830360413,
      "y": 0.687900960445404,
      "z": 0.0,
      "corr_price": -0.24388905007041511,
      "mean": 5.4401972947014565,
      "std": 2.7845546952110287,
      "latest": 3.2
    },
    {
      "id": "ws_101794",
      "label": "ws_101794",
      "group": "wind_speed",
      "x": 0.937123715877533,
      "y": 0.5412891507148743,
      "z": 0.0348089225590229,
      "corr_price": -0.23238496441427242,
      "mean": 4.6423483271970545,
      "std": 2.405253515194008,
      "latest": 2.1
    },
    {
      "id": "ws_101786",
      "label": "ws_101786",
      "group": "wind_speed",
      "x": 0.9636066555976868,
      "y": 0.5275970101356506,
      "z": 0.1768631786108017,
      "corr_price": -0.2729556938204066,
      "mean": 3.673919481351048,
      "std": 1.9458771860759967,
      "latest": 2.1
    },
    {
      "id": "ws_101840",
      "label": "ws_101840",
      "group": "wind_speed",
      "x": 0.9435092210769653,
      "y": 0.5605698227882385,
      "z": 0.019823798909783363,
      "corr_price": -0.23602135921087053,
      "mean": 3.465342030841471,
      "std": 1.9198234057759922,
      "latest": 0.9
    },
    {
      "id": "ws_101783",
      "label": "ws_101783",
      "group": "wind_speed",
      "x": 0.91810142993927,
      "y": 0.6335796117782593,
      "z": 0.03628489747643471,
      "corr_price": -0.2291920737973731,
      "mean": 7.114194813510485,
      "std": 3.4488440182174824,
      "latest": 1.6
    },
    {
      "id": "ws_101846",
      "label": "ws_101846",
      "group": "wind_speed",
      "x": 0.9324519634246826,
      "y": 0.5021209716796875,
      "z": 0.0022972289007157087,
      "corr_price": -0.21026042960014926,
      "mean": 5.241439891147751,
      "std": 2.7968059641776164,
      "latest": 1.4
    },
    {
      "id": "ws_101986",
      "label": "ws_101986",
      "group": "wind_speed",
      "x": 0.9568250775337219,
      "y": 0.5583506226539612,
      "z": 0.11268597841262817,
      "corr_price": -0.24161211848242936,
      "mean": 3.1037738114294857,
      "std": 1.8591201151169483,
      "latest": 3.1
    },
    {
      "id": "ws_101537",
      "label": "ws_101537",
      "group": "wind_speed",
      "x": 0.9684196710586548,
      "y": 0.49594926834106445,
      "z": 0.23719103634357452,
      "corr_price": -0.21132153562539518,
      "mean": 1.9532135425004,
      "std": 1.1698860722925621,
      "latest": 2.0
    },
    {
      "id": "ws_101570",
      "label": "ws_101570",
      "group": "wind_speed",
      "x": 0.986367404460907,
      "y": 0.41666460037231445,
      "z": 0.24254024028778076,
      "corr_price": -0.2684813876629082,
      "mean": 3.555906835280935,
      "std": 1.8947580262064814,
      "latest": 2.4
    },
    {
      "id": "ws_101608",
      "label": "ws_101608",
      "group": "wind_speed",
      "x": 0.9923076033592224,
      "y": 0.369881808757782,
      "z": 0.26977095007896423,
      "corr_price": -0.22298497004219991,
      "mean": 3.4405194493356817,
      "std": 1.7724945686969011,
      "latest": 2.5
    },
    {
      "id": "ws_101191",
      "label": "ws_101191",
      "group": "wind_speed",
      "x": 0.9997179508209229,
      "y": 0.2845418453216553,
      "z": 0.3347196877002716,
      "corr_price": -0.1899479081670655,
      "mean": 3.600796382263487,
      "std": 1.6586158835822622,
      "latest": 0.5
    },
    {
      "id": "ws_101237",
      "label": "ws_101237",
      "group": "wind_speed",
      "x": 1.0,
      "y": 0.3573012351989746,
      "z": 0.30020421743392944,
      "corr_price": -0.1424047424131554,
      "mean": 3.2884984792700496,
      "std": 1.5988276888105772,
      "latest": 0.6
    }
  ],
  "samples": 24988
}